[
	{
		"id" : 1,
		"verb_id" : 1,
		"tense" : "presente",
		"mood" : "indicative",
		"aspect" : null,
		"voice" : null,
		"person" : "1sg",
		"number" : "sg",
		"polypersonal_subject" : null,
		"polypersonal_dobj" : null,
		"polypersonal_iobj" : null,
		"conjugated_form" : "ვცხოვრობ",
		"normalized_form" : "ვცხოვრობ",
		"morphemes" : "[\"ვ\", \"ცხოვრ\", \"ობ\"]",
		"ipa" : null,
		"audio_url" : null,
		"notes" : null,
		"created_at" : "2025-08-29T14:39:09.000Z"
	},
	{
		"id" : 2,
		"verb_id" : 1,
		"tense" : "presente",
		"mood" : "indicative",
		"aspect" : null,
		"voice" : null,
		"person" : "2sg",
		"number" : "sg",
		"polypersonal_subject" : null,
		"polypersonal_dobj" : null,
		"polypersonal_iobj" : null,
		"conjugated_form" : "ცხოვრობ",
		"normalized_form" : "ცხოვრობ",
		"morphemes" : "[\"ცხოვრ\", \"ობ\"]",
		"ipa" : null,
		"audio_url" : null,
		"notes" : null,
		"created_at" : "2025-08-29T14:39:09.000Z"
	},
	{
		"id" : 3,
		"verb_id" : 1,
		"tense" : "presente",
		"mood" : "indicative",
		"aspect" : null,
		"voice" : null,
		"person" : "3sg",
		"number" : "sg",
		"polypersonal_subject" : null,
		"polypersonal_dobj" : null,
		"polypersonal_iobj" : null,
		"conjugated_form" : "ცხოვრობს",
		"normalized_form" : "ცხოვრობს",
		"morphemes" : "[\"ცხოვრ\", \"ობ\", \"ს\"]",
		"ipa" : null,
		"audio_url" : null,
		"notes" : null,
		"created_at" : "2025-08-29T14:39:09.000Z"
	},
	{
		"id" : 4,
		"verb_id" : 1,
		"tense" : "presente",
		"mood" : "indicative",
		"aspect" : null,
		"voice" : null,
		"person" : "1pl",
		"number" : "pl",
		"polypersonal_subject" : null,
		"polypersonal_dobj" : null,
		"polypersonal_iobj" : null,
		"conjugated_form" : "ვცხოვრობთ",
		"normalized_form" : "ვცხოვრობთ",
		"morphemes" : "[\"ვ\", \"ცხოვრ\", \"ობ\", \"თ\"]",
		"ipa" : null,
		"audio_url" : null,
		"notes" : null,
		"created_at" : "2025-08-29T14:39:09.000Z"
	},
	{
		"id" : 5,
		"verb_id" : 1,
		"tense" : "presente",
		"mood" : "indicative",
		"aspect" : null,
		"voice" : null,
		"person" : "2pl",
		"number" : "pl",
		"polypersonal_subject" : null,
		"polypersonal_dobj" : null,
		"polypersonal_iobj" : null,
		"conjugated_form" : "ცხოვრობთ",
		"normalized_form" : "ცხოვრობთ",
		"morphemes" : "[\"ცხოვრ\", \"ობ\", \"თ\"]",
		"ipa" : null,
		"audio_url" : null,
		"notes" : null,
		"created_at" : "2025-08-29T14:39:09.000Z"
	},
	{
		"id" : 6,
		"verb_id" : 1,
		"tense" : "presente",
		"mood" : "indicative",
		"aspect" : null,
		"voice" : null,
		"person" : "3pl",
		"number" : "pl",
		"polypersonal_subject" : null,
		"polypersonal_dobj" : null,
		"polypersonal_iobj" : null,
		"conjugated_form" : "ცხოვრობენ",
		"normalized_form" : "ცხოვრობენ",
		"morphemes" : "[\"ცხოვრ\", \"ობ\", \"ენ\"]",
		"ipa" : null,
		"audio_url" : null,
		"notes" : null,
		"created_at" : "2025-08-29T14:39:09.000Z"
	},
	{
		"id" : 7,
		"verb_id" : 1,
		"tense" : "imperfect",
		"mood" : "indicative",
		"aspect" : null,
		"voice" : null,
		"person" : "1sg",
		"number" : "sg",
		"polypersonal_subject" : null,
		"polypersonal_dobj" : null,
		"polypersonal_iobj" : null,
		"conjugated_form" : "ვცხოვრობდი",
		"normalized_form" : "ვცხოვრობდი",
		"morphemes" : "[\"ვ\", \"ცხოვრ\", \"ობ\", \"დ\", \"ი\"]",
		"ipa" : null,
		"audio_url" : null,
		"notes" : null,
		"created_at" : "2025-08-29T14:39:09.000Z"
	},
	{
		"id" : 8,
		"verb_id" : 1,
		"tense" : "imperfect",
		"mood" : "indicative",
		"aspect" : null,
		"voice" : null,
		"person" : "2sg",
		"number" : "sg",
		"polypersonal_subject" : null,
		"polypersonal_dobj" : null,
		"polypersonal_iobj" : null,
		"conjugated_form" : "ცხოვრობდი",
		"normalized_form" : "ცხოვრობდი",
		"morphemes" : "[\"ცხოვრ\", \"ობ\", \"დ\", \"ი\"]",
		"ipa" : null,
		"audio_url" : null,
		"notes" : null,
		"created_at" : "2025-08-29T14:39:09.000Z"
	},
	{
		"id" : 9,
		"verb_id" : 1,
		"tense" : "imperfect",
		"mood" : "indicative",
		"aspect" : null,
		"voice" : null,
		"person" : "3sg",
		"number" : "sg",
		"polypersonal_subject" : null,
		"polypersonal_dobj" : null,
		"polypersonal_iobj" : null,
		"conjugated_form" : "ცხოვრობდა",
		"normalized_form" : "ცხოვრობდა",
		"morphemes" : "[\"ცხოვრ\", \"ობ\", \"დ\", \"ა\"]",
		"ipa" : null,
		"audio_url" : null,
		"notes" : null,
		"created_at" : "2025-08-29T14:39:09.000Z"
	},
	{
		"id" : 10,
		"verb_id" : 1,
		"tense" : "imperfect",
		"mood" : "indicative",
		"aspect" : null,
		"voice" : null,
		"person" : "1pl",
		"number" : "pl",
		"polypersonal_subject" : null,
		"polypersonal_dobj" : null,
		"polypersonal_iobj" : null,
		"conjugated_form" : "ვცხოვრობდით",
		"normalized_form" : "ვცხოვრობდით",
		"morphemes" : "[\"ვ\", \"ცხოვრ\", \"ობ\", \"დ\", \"ით\"]",
		"ipa" : null,
		"audio_url" : null,
		"notes" : null,
		"created_at" : "2025-08-29T14:39:09.000Z"
	},
	{
		"id" : 11,
		"verb_id" : 1,
		"tense" : "imperfect",
		"mood" : "indicative",
		"aspect" : null,
		"voice" : null,
		"person" : "2pl",
		"number" : "pl",
		"polypersonal_subject" : null,
		"polypersonal_dobj" : null,
		"polypersonal_iobj" : null,
		"conjugated_form" : "ცხოვრობდით",
		"normalized_form" : "ცხოვრობდით",
		"morphemes" : "[\"ცხოვრ\", \"ობ\", \"დ\", \"ით\"]",
		"ipa" : null,
		"audio_url" : null,
		"notes" : null,
		"created_at" : "2025-08-29T14:39:09.000Z"
	},
	{
		"id" : 12,
		"verb_id" : 1,
		"tense" : "imperfect",
		"mood" : "indicative",
		"aspect" : null,
		"voice" : null,
		"person" : "3pl",
		"number" : "pl",
		"polypersonal_subject" : null,
		"polypersonal_dobj" : null,
		"polypersonal_iobj" : null,
		"conjugated_form" : "ცხოვრობდნენ",
		"normalized_form" : "ცხოვრობდნენ",
		"morphemes" : "[\"ცხოვრ\", \"ობ\", \"დ\", \"ნენ\"]",
		"ipa" : null,
		"audio_url" : null,
		"notes" : null,
		"created_at" : "2025-08-29T14:39:09.000Z"
	},
	{
		"id" : 13,
		"verb_id" : 1,
		"tense" : "present",
		"mood" : "subjunctive",
		"aspect" : null,
		"voice" : null,
		"person" : "1sg",
		"number" : "sg",
		"polypersonal_subject" : null,
		"polypersonal_dobj" : null,
		"polypersonal_iobj" : null,
		"conjugated_form" : "ვცხოვრობდე",
		"normalized_form" : "ვცხოვრობდე",
		"morphemes" : "[\"ვ\", \"ცხოვრ\", \"ობ\", \"დ\", \"ე\"]",
		"ipa" : null,
		"audio_url" : null,
		"notes" : null,
		"created_at" : "2025-08-29T14:39:09.000Z"
	},
	{
		"id" : 14,
		"verb_id" : 1,
		"tense" : "present",
		"mood" : "subjunctive",
		"aspect" : null,
		"voice" : null,
		"person" : "2sg",
		"number" : "sg",
		"polypersonal_subject" : null,
		"polypersonal_dobj" : null,
		"polypersonal_iobj" : null,
		"conjugated_form" : "ცხოვრობდე",
		"normalized_form" : "ცხოვრობდე",
		"morphemes" : "[\"ცხოვრ\", \"ობ\", \"დ\", \"ე\"]",
		"ipa" : null,
		"audio_url" : null,
		"notes" : null,
		"created_at" : "2025-08-29T14:39:09.000Z"
	},
	{
		"id" : 15,
		"verb_id" : 1,
		"tense" : "present",
		"mood" : "subjunctive",
		"aspect" : null,
		"voice" : null,
		"person" : "3sg",
		"number" : "sg",
		"polypersonal_subject" : null,
		"polypersonal_dobj" : null,
		"polypersonal_iobj" : null,
		"conjugated_form" : "ცხოვრობდეს",
		"normalized_form" : "ცხოვრობდეს",
		"morphemes" : "[\"ცხოვრ\", \"ობ\", \"დ\", \"ეს\"]",
		"ipa" : null,
		"audio_url" : null,
		"notes" : null,
		"created_at" : "2025-08-29T14:39:09.000Z"
	},
	{
		"id" : 16,
		"verb_id" : 1,
		"tense" : "present",
		"mood" : "subjunctive",
		"aspect" : null,
		"voice" : null,
		"person" : "1pl",
		"number" : "pl",
		"polypersonal_subject" : null,
		"polypersonal_dobj" : null,
		"polypersonal_iobj" : null,
		"conjugated_form" : "ვცხოვრობდეთ",
		"normalized_form" : "ვცხოვრობდეთ",
		"morphemes" : "[\"ვ\", \"ცხოვრ\", \"ობ\", \"დ\", \"ეთ\"]",
		"ipa" : null,
		"audio_url" : null,
		"notes" : null,
		"created_at" : "2025-08-29T14:39:09.000Z"
	},
	{
		"id" : 17,
		"verb_id" : 1,
		"tense" : "present",
		"mood" : "subjunctive",
		"aspect" : null,
		"voice" : null,
		"person" : "2pl",
		"number" : "pl",
		"polypersonal_subject" : null,
		"polypersonal_dobj" : null,
		"polypersonal_iobj" : null,
		"conjugated_form" : "ცხოვრობდეთ",
		"normalized_form" : "ცხოვრობდეთ",
		"morphemes" : "[\"ცხოვრ\", \"ობ\", \"დ\", \"ეთ\"]",
		"ipa" : null,
		"audio_url" : null,
		"notes" : null,
		"created_at" : "2025-08-29T14:39:09.000Z"
	},
	{
		"id" : 18,
		"verb_id" : 1,
		"tense" : "present",
		"mood" : "subjunctive",
		"aspect" : null,
		"voice" : null,
		"person" : "3pl",
		"number" : "pl",
		"polypersonal_subject" : null,
		"polypersonal_dobj" : null,
		"polypersonal_iobj" : null,
		"conjugated_form" : "ცხოვრობდნენ",
		"normalized_form" : "ცხოვრობდნენ",
		"morphemes" : "[\"ცხოვრ\", \"ობ\", \"დ\", \"ნენ\"]",
		"ipa" : null,
		"audio_url" : null,
		"notes" : null,
		"created_at" : "2025-08-29T14:39:09.000Z"
	},
	{
		"id" : 19,
		"verb_id" : 1,
		"tense" : "future",
		"mood" : "indicative",
		"aspect" : null,
		"voice" : null,
		"person" : "1sg",
		"number" : "sg",
		"polypersonal_subject" : null,
		"polypersonal_dobj" : null,
		"polypersonal_iobj" : null,
		"conjugated_form" : "ვიცხოვრებ",
		"normalized_form" : "ვიცხოვრებ",
		"morphemes" : "[\"ვ\", \"ი\", \"ცხოვრ\", \"ებ\"]",
		"ipa" : null,
		"audio_url" : null,
		"notes" : null,
		"created_at" : "2025-08-29T14:39:09.000Z"
	},
	{
		"id" : 20,
		"verb_id" : 1,
		"tense" : "future",
		"mood" : "indicative",
		"aspect" : null,
		"voice" : null,
		"person" : "2sg",
		"number" : "sg",
		"polypersonal_subject" : null,
		"polypersonal_dobj" : null,
		"polypersonal_iobj" : null,
		"conjugated_form" : "იცხოვრებ",
		"normalized_form" : "იცხოვრებ",
		"morphemes" : "[\"ი\", \"ცხოვრ\", \"ებ\"]",
		"ipa" : null,
		"audio_url" : null,
		"notes" : null,
		"created_at" : "2025-08-29T14:39:09.000Z"
	},
	{
		"id" : 21,
		"verb_id" : 1,
		"tense" : "future",
		"mood" : "indicative",
		"aspect" : null,
		"voice" : null,
		"person" : "3sg",
		"number" : "sg",
		"polypersonal_subject" : null,
		"polypersonal_dobj" : null,
		"polypersonal_iobj" : null,
		"conjugated_form" : "იცხოვრებს",
		"normalized_form" : "იცხოვრებს",
		"morphemes" : "[\"ი\", \"ცხოვრ\", \"ებ\", \"ს\"]",
		"ipa" : null,
		"audio_url" : null,
		"notes" : null,
		"created_at" : "2025-08-29T14:39:09.000Z"
	},
	{
		"id" : 22,
		"verb_id" : 1,
		"tense" : "future",
		"mood" : "indicative",
		"aspect" : null,
		"voice" : null,
		"person" : "1pl",
		"number" : "pl",
		"polypersonal_subject" : null,
		"polypersonal_dobj" : null,
		"polypersonal_iobj" : null,
		"conjugated_form" : "ვიცხოვრებთ",
		"normalized_form" : "ვიცხოვრებთ",
		"morphemes" : "[\"ვ\", \"ი\", \"ცხოვრ\", \"ებ\", \"თ\"]",
		"ipa" : null,
		"audio_url" : null,
		"notes" : null,
		"created_at" : "2025-08-29T14:39:09.000Z"
	},
	{
		"id" : 23,
		"verb_id" : 1,
		"tense" : "future",
		"mood" : "indicative",
		"aspect" : null,
		"voice" : null,
		"person" : "2pl",
		"number" : "pl",
		"polypersonal_subject" : null,
		"polypersonal_dobj" : null,
		"polypersonal_iobj" : null,
		"conjugated_form" : "იცხოვრებთ",
		"normalized_form" : "იცხოვრებთ",
		"morphemes" : "[\"ი\", \"ცხოვრ\", \"ებ\", \"თ\"]",
		"ipa" : null,
		"audio_url" : null,
		"notes" : null,
		"created_at" : "2025-08-29T14:39:09.000Z"
	},
	{
		"id" : 24,
		"verb_id" : 1,
		"tense" : "future",
		"mood" : "indicative",
		"aspect" : null,
		"voice" : null,
		"person" : "3pl",
		"number" : "pl",
		"polypersonal_subject" : null,
		"polypersonal_dobj" : null,
		"polypersonal_iobj" : null,
		"conjugated_form" : "იცხოვრებენ",
		"normalized_form" : "იცხოვრებენ",
		"morphemes" : "[\"ი\", \"ცხოვრ\", \"ებ\", \"ენ\"]",
		"ipa" : null,
		"audio_url" : null,
		"notes" : null,
		"created_at" : "2025-08-29T14:39:09.000Z"
	},
	{
		"id" : 25,
		"verb_id" : 1,
		"tense" : "conditional",
		"mood" : "conditional",
		"aspect" : null,
		"voice" : null,
		"person" : "1sg",
		"number" : "sg",
		"polypersonal_subject" : null,
		"polypersonal_dobj" : null,
		"polypersonal_iobj" : null,
		"conjugated_form" : "ვიცხოვრებდი",
		"normalized_form" : "ვიცხოვრებდი",
		"morphemes" : "[\"ვ\", \"ი\", \"ცხოვრ\", \"ებ\", \"დ\", \"ი\"]",
		"ipa" : null,
		"audio_url" : null,
		"notes" : null,
		"created_at" : "2025-08-29T14:39:09.000Z"
	},
	{
		"id" : 26,
		"verb_id" : 1,
		"tense" : "conditional",
		"mood" : "conditional",
		"aspect" : null,
		"voice" : null,
		"person" : "2sg",
		"number" : "sg",
		"polypersonal_subject" : null,
		"polypersonal_dobj" : null,
		"polypersonal_iobj" : null,
		"conjugated_form" : "იცხოვრებდი",
		"normalized_form" : "იცხოვრებდი",
		"morphemes" : "[\"ი\", \"ცხოვრ\", \"ებ\", \"დ\", \"ი\"]",
		"ipa" : null,
		"audio_url" : null,
		"notes" : null,
		"created_at" : "2025-08-29T14:39:09.000Z"
	},
	{
		"id" : 27,
		"verb_id" : 1,
		"tense" : "conditional",
		"mood" : "conditional",
		"aspect" : null,
		"voice" : null,
		"person" : "3sg",
		"number" : "sg",
		"polypersonal_subject" : null,
		"polypersonal_dobj" : null,
		"polypersonal_iobj" : null,
		"conjugated_form" : "იცხოვრებდა",
		"normalized_form" : "იცხოვრებდა",
		"morphemes" : "[\"ი\", \"ცხოვრ\", \"ებ\", \"დ\", \"ა\"]",
		"ipa" : null,
		"audio_url" : null,
		"notes" : null,
		"created_at" : "2025-08-29T14:39:09.000Z"
	},
	{
		"id" : 28,
		"verb_id" : 1,
		"tense" : "conditional",
		"mood" : "conditional",
		"aspect" : null,
		"voice" : null,
		"person" : "1pl",
		"number" : "pl",
		"polypersonal_subject" : null,
		"polypersonal_dobj" : null,
		"polypersonal_iobj" : null,
		"conjugated_form" : "ვიცხოვრებდით",
		"normalized_form" : "ვიცხოვრებდით",
		"morphemes" : "[\"ვ\", \"ი\", \"ცხოვრ\", \"ებ\", \"დ\", \"ით\"]",
		"ipa" : null,
		"audio_url" : null,
		"notes" : null,
		"created_at" : "2025-08-29T14:39:09.000Z"
	},
	{
		"id" : 29,
		"verb_id" : 1,
		"tense" : "conditional",
		"mood" : "conditional",
		"aspect" : null,
		"voice" : null,
		"person" : "2pl",
		"number" : "pl",
		"polypersonal_subject" : null,
		"polypersonal_dobj" : null,
		"polypersonal_iobj" : null,
		"conjugated_form" : "იცხოვრებდით",
		"normalized_form" : "იცხოვრებდით",
		"morphemes" : "[\"ი\", \"ცხოვრ\", \"ებ\", \"დ\", \"ით\"]",
		"ipa" : null,
		"audio_url" : null,
		"notes" : null,
		"created_at" : "2025-08-29T14:39:09.000Z"
	},
	{
		"id" : 30,
		"verb_id" : 1,
		"tense" : "conditional",
		"mood" : "conditional",
		"aspect" : null,
		"voice" : null,
		"person" : "3pl",
		"number" : "pl",
		"polypersonal_subject" : null,
		"polypersonal_dobj" : null,
		"polypersonal_iobj" : null,
		"conjugated_form" : "იცხოვრებდნენ",
		"normalized_form" : "იცხოვრებდნენ",
		"morphemes" : "[\"ი\", \"ცხოვრ\", \"ებ\", \"დ\", \"ნენ\"]",
		"ipa" : null,
		"audio_url" : null,
		"notes" : null,
		"created_at" : "2025-08-29T14:39:09.000Z"
	},
	{
		"id" : 31,
		"verb_id" : 1,
		"tense" : "future",
		"mood" : "subjunctive",
		"aspect" : null,
		"voice" : null,
		"person" : "1sg",
		"number" : "sg",
		"polypersonal_subject" : null,
		"polypersonal_dobj" : null,
		"polypersonal_iobj" : null,
		"conjugated_form" : "ვიცხოვრებდე",
		"normalized_form" : "ვიცხოვრებდე",
		"morphemes" : "[\"ვ\", \"ი\", \"ცხოვრ\", \"ებ\", \"დ\", \"ე\"]",
		"ipa" : null,
		"audio_url" : null,
		"notes" : null,
		"created_at" : "2025-08-29T14:39:09.000Z"
	},
	{
		"id" : 32,
		"verb_id" : 1,
		"tense" : "future",
		"mood" : "subjunctive",
		"aspect" : null,
		"voice" : null,
		"person" : "2sg",
		"number" : "sg",
		"polypersonal_subject" : null,
		"polypersonal_dobj" : null,
		"polypersonal_iobj" : null,
		"conjugated_form" : "იცხოვრებდე",
		"normalized_form" : "იცხოვრებდე",
		"morphemes" : "[\"ი\", \"ცხოვრ\", \"ებ\", \"დ\", \"ე\"]",
		"ipa" : null,
		"audio_url" : null,
		"notes" : null,
		"created_at" : "2025-08-29T14:39:09.000Z"
	},
	{
		"id" : 33,
		"verb_id" : 1,
		"tense" : "future",
		"mood" : "subjunctive",
		"aspect" : null,
		"voice" : null,
		"person" : "3sg",
		"number" : "sg",
		"polypersonal_subject" : null,
		"polypersonal_dobj" : null,
		"polypersonal_iobj" : null,
		"conjugated_form" : "იცხოვრებდეს",
		"normalized_form" : "იცხოვრებდეს",
		"morphemes" : "[\"ი\", \"ცხოვრ\", \"ებ\", \"დ\", \"ეს\"]",
		"ipa" : null,
		"audio_url" : null,
		"notes" : null,
		"created_at" : "2025-08-29T14:39:09.000Z"
	},
	{
		"id" : 34,
		"verb_id" : 1,
		"tense" : "future",
		"mood" : "subjunctive",
		"aspect" : null,
		"voice" : null,
		"person" : "1pl",
		"number" : "pl",
		"polypersonal_subject" : null,
		"polypersonal_dobj" : null,
		"polypersonal_iobj" : null,
		"conjugated_form" : "ვიცხოვრებდეთ",
		"normalized_form" : "ვიცხოვრებდეთ",
		"morphemes" : "[\"ვ\", \"ი\", \"ცხოვრ\", \"ებ\", \"დ\", \"ეთ\"]",
		"ipa" : null,
		"audio_url" : null,
		"notes" : null,
		"created_at" : "2025-08-29T14:39:09.000Z"
	},
	{
		"id" : 35,
		"verb_id" : 1,
		"tense" : "future",
		"mood" : "subjunctive",
		"aspect" : null,
		"voice" : null,
		"person" : "2pl",
		"number" : "pl",
		"polypersonal_subject" : null,
		"polypersonal_dobj" : null,
		"polypersonal_iobj" : null,
		"conjugated_form" : "იცხოვრებდეთ",
		"normalized_form" : "იცხოვრებდეთ",
		"morphemes" : "[\"ი\", \"ცხოვრ\", \"ებ\", \"დ\", \"ეთ\"]",
		"ipa" : null,
		"audio_url" : null,
		"notes" : null,
		"created_at" : "2025-08-29T14:39:09.000Z"
	},
	{
		"id" : 36,
		"verb_id" : 1,
		"tense" : "future",
		"mood" : "subjunctive",
		"aspect" : null,
		"voice" : null,
		"person" : "3pl",
		"number" : "pl",
		"polypersonal_subject" : null,
		"polypersonal_dobj" : null,
		"polypersonal_iobj" : null,
		"conjugated_form" : "იცხოვრებდნენ",
		"normalized_form" : "იცხოვრებდნენ",
		"morphemes" : "[\"ი\", \"ცხოვრ\", \"ებ\", \"დ\", \"ნენ\"]",
		"ipa" : null,
		"audio_url" : null,
		"notes" : null,
		"created_at" : "2025-08-29T14:39:09.000Z"
	},
	{
		"id" : 37,
		"verb_id" : 1,
		"tense" : "aorist",
		"mood" : "aorist",
		"aspect" : null,
		"voice" : null,
		"person" : "1sg",
		"number" : "sg",
		"polypersonal_subject" : null,
		"polypersonal_dobj" : null,
		"polypersonal_iobj" : null,
		"conjugated_form" : "ვიცხოვრე",
		"normalized_form" : "ვიცხოვრე",
		"morphemes" : "[\"ვ\", \"ი\", \"ცხოვრ\", \"ე\"]",
		"ipa" : null,
		"audio_url" : null,
		"notes" : null,
		"created_at" : "2025-08-29T14:39:09.000Z"
	},
	{
		"id" : 38,
		"verb_id" : 1,
		"tense" : "aorist",
		"mood" : "aorist",
		"aspect" : null,
		"voice" : null,
		"person" : "2sg",
		"number" : "sg",
		"polypersonal_subject" : null,
		"polypersonal_dobj" : null,
		"polypersonal_iobj" : null,
		"conjugated_form" : "იცხოვრე",
		"normalized_form" : "იცხოვრე",
		"morphemes" : "[\"ი\", \"ცხოვრ\", \"ე\"]",
		"ipa" : null,
		"audio_url" : null,
		"notes" : null,
		"created_at" : "2025-08-29T14:39:09.000Z"
	},
	{
		"id" : 39,
		"verb_id" : 1,
		"tense" : "aorist",
		"mood" : "aorist",
		"aspect" : null,
		"voice" : null,
		"person" : "3sg",
		"number" : "sg",
		"polypersonal_subject" : null,
		"polypersonal_dobj" : null,
		"polypersonal_iobj" : null,
		"conjugated_form" : "იცხოვრა",
		"normalized_form" : "იცხოვრა",
		"morphemes" : "[\"ი\", \"ცხოვრ\", \"ა\"]",
		"ipa" : null,
		"audio_url" : null,
		"notes" : null,
		"created_at" : "2025-08-29T14:39:09.000Z"
	},
	{
		"id" : 40,
		"verb_id" : 1,
		"tense" : "aorist",
		"mood" : "aorist",
		"aspect" : null,
		"voice" : null,
		"person" : "1pl",
		"number" : "pl",
		"polypersonal_subject" : null,
		"polypersonal_dobj" : null,
		"polypersonal_iobj" : null,
		"conjugated_form" : "ვიცხოვრეთ",
		"normalized_form" : "ვიცხოვრეთ",
		"morphemes" : "[\"ვ\", \"ი\", \"ცხოვრ\", \"ეთ\"]",
		"ipa" : null,
		"audio_url" : null,
		"notes" : null,
		"created_at" : "2025-08-29T14:39:09.000Z"
	},
	{
		"id" : 41,
		"verb_id" : 1,
		"tense" : "aorist",
		"mood" : "aorist",
		"aspect" : null,
		"voice" : null,
		"person" : "2pl",
		"number" : "pl",
		"polypersonal_subject" : null,
		"polypersonal_dobj" : null,
		"polypersonal_iobj" : null,
		"conjugated_form" : "იცხოვრეთ",
		"normalized_form" : "იცხოვრეთ",
		"morphemes" : "[\"ი\", \"ცხოვრ\", \"ეთ\"]",
		"ipa" : null,
		"audio_url" : null,
		"notes" : null,
		"created_at" : "2025-08-29T14:39:09.000Z"
	},
	{
		"id" : 42,
		"verb_id" : 1,
		"tense" : "aorist",
		"mood" : "aorist",
		"aspect" : null,
		"voice" : null,
		"person" : "3pl",
		"number" : "pl",
		"polypersonal_subject" : null,
		"polypersonal_dobj" : null,
		"polypersonal_iobj" : null,
		"conjugated_form" : "იცხოვრეს",
		"normalized_form" : "იცხოვრეს",
		"morphemes" : "[\"ი\", \"ცხოვრ\", \"ეს\"]",
		"ipa" : null,
		"audio_url" : null,
		"notes" : null,
		"created_at" : "2025-08-29T14:39:09.000Z"
	},
	{
		"id" : 43,
		"verb_id" : 1,
		"tense" : "optative",
		"mood" : "optative",
		"aspect" : null,
		"voice" : null,
		"person" : "1sg",
		"number" : "sg",
		"polypersonal_subject" : null,
		"polypersonal_dobj" : null,
		"polypersonal_iobj" : null,
		"conjugated_form" : "ვიცხოვრო",
		"normalized_form" : "ვიცხოვრო",
		"morphemes" : "[\"ვ\", \"ი\", \"ცხოვრ\", \"ო\"]",
		"ipa" : null,
		"audio_url" : null,
		"notes" : null,
		"created_at" : "2025-08-29T14:39:09.000Z"
	},
	{
		"id" : 44,
		"verb_id" : 1,
		"tense" : "optative",
		"mood" : "optative",
		"aspect" : null,
		"voice" : null,
		"person" : "2sg",
		"number" : "sg",
		"polypersonal_subject" : null,
		"polypersonal_dobj" : null,
		"polypersonal_iobj" : null,
		"conjugated_form" : "იცხოვრო",
		"normalized_form" : "იცხოვრო",
		"morphemes" : "[\"ი\", \"ცხოვრ\", \"ო\"]",
		"ipa" : null,
		"audio_url" : null,
		"notes" : null,
		"created_at" : "2025-08-29T14:39:09.000Z"
	},
	{
		"id" : 45,
		"verb_id" : 1,
		"tense" : "optative",
		"mood" : "optative",
		"aspect" : null,
		"voice" : null,
		"person" : "3sg",
		"number" : "sg",
		"polypersonal_subject" : null,
		"polypersonal_dobj" : null,
		"polypersonal_iobj" : null,
		"conjugated_form" : "იცხოვროს",
		"normalized_form" : "იცხოვროს",
		"morphemes" : "[\"ი\", \"ცხოვრ\", \"ოს\"]",
		"ipa" : null,
		"audio_url" : null,
		"notes" : null,
		"created_at" : "2025-08-29T14:39:09.000Z"
	},
	{
		"id" : 46,
		"verb_id" : 1,
		"tense" : "optative",
		"mood" : "optative",
		"aspect" : null,
		"voice" : null,
		"person" : "1pl",
		"number" : "pl",
		"polypersonal_subject" : null,
		"polypersonal_dobj" : null,
		"polypersonal_iobj" : null,
		"conjugated_form" : "ვიცხოვროთ",
		"normalized_form" : "ვიცხოვროთ",
		"morphemes" : "[\"ვ\", \"ი\", \"ცხოვრ\", \"ოთ\"]",
		"ipa" : null,
		"audio_url" : null,
		"notes" : null,
		"created_at" : "2025-08-29T14:39:09.000Z"
	},
	{
		"id" : 47,
		"verb_id" : 1,
		"tense" : "optative",
		"mood" : "optative",
		"aspect" : null,
		"voice" : null,
		"person" : "2pl",
		"number" : "pl",
		"polypersonal_subject" : null,
		"polypersonal_dobj" : null,
		"polypersonal_iobj" : null,
		"conjugated_form" : "იცხოვროთ",
		"normalized_form" : "იცხოვროთ",
		"morphemes" : "[\"ი\", \"ცხოვრ\", \"ოთ\"]",
		"ipa" : null,
		"audio_url" : null,
		"notes" : null,
		"created_at" : "2025-08-29T14:39:09.000Z"
	},
	{
		"id" : 48,
		"verb_id" : 1,
		"tense" : "optative",
		"mood" : "optative",
		"aspect" : null,
		"voice" : null,
		"person" : "3pl",
		"number" : "pl",
		"polypersonal_subject" : null,
		"polypersonal_dobj" : null,
		"polypersonal_iobj" : null,
		"conjugated_form" : "იცხოვრონ",
		"normalized_form" : "იცხოვრონ",
		"morphemes" : "[\"ი\", \"ცხოვრ\", \"ონ\"]",
		"ipa" : null,
		"audio_url" : null,
		"notes" : null,
		"created_at" : "2025-08-29T14:39:09.000Z"
	},
	{
		"id" : 49,
		"verb_id" : 1,
		"tense" : "perfect",
		"mood" : "indicative",
		"aspect" : null,
		"voice" : null,
		"person" : "1sg",
		"number" : "sg",
		"polypersonal_subject" : null,
		"polypersonal_dobj" : null,
		"polypersonal_iobj" : null,
		"conjugated_form" : "მიცხოვრია",
		"normalized_form" : "მიცხოვრია",
		"morphemes" : "[\"მი\", \"ცხოვრ\", \"ია\"]",
		"ipa" : null,
		"audio_url" : null,
		"notes" : null,
		"created_at" : "2025-08-29T14:39:09.000Z"
	},
	{
		"id" : 50,
		"verb_id" : 1,
		"tense" : "perfect",
		"mood" : "indicative",
		"aspect" : null,
		"voice" : null,
		"person" : "2sg",
		"number" : "sg",
		"polypersonal_subject" : null,
		"polypersonal_dobj" : null,
		"polypersonal_iobj" : null,
		"conjugated_form" : "გიცხოვრია",
		"normalized_form" : "გიცხოვრია",
		"morphemes" : "[\"გი\", \"ცხოვრ\", \"ია\"]",
		"ipa" : null,
		"audio_url" : null,
		"notes" : null,
		"created_at" : "2025-08-29T14:39:09.000Z"
	},
	{
		"id" : 51,
		"verb_id" : 1,
		"tense" : "perfect",
		"mood" : "indicative",
		"aspect" : null,
		"voice" : null,
		"person" : "3sg",
		"number" : "sg",
		"polypersonal_subject" : null,
		"polypersonal_dobj" : null,
		"polypersonal_iobj" : null,
		"conjugated_form" : "უცხოვრია",
		"normalized_form" : "უცხოვრია",
		"morphemes" : "[\"უ\", \"ცხოვრ\", \"ია\"]",
		"ipa" : null,
		"audio_url" : null,
		"notes" : null,
		"created_at" : "2025-08-29T14:39:09.000Z"
	},
	{
		"id" : 52,
		"verb_id" : 1,
		"tense" : "perfect",
		"mood" : "indicative",
		"aspect" : null,
		"voice" : null,
		"person" : "1pl",
		"number" : "pl",
		"polypersonal_subject" : null,
		"polypersonal_dobj" : null,
		"polypersonal_iobj" : null,
		"conjugated_form" : "გვიცხოვრია",
		"normalized_form" : "გვიცხოვრია",
		"morphemes" : "[\"გვი\", \"ცხოვრ\", \"ია\"]",
		"ipa" : null,
		"audio_url" : null,
		"notes" : null,
		"created_at" : "2025-08-29T14:39:09.000Z"
	},
	{
		"id" : 53,
		"verb_id" : 1,
		"tense" : "perfect",
		"mood" : "indicative",
		"aspect" : null,
		"voice" : null,
		"person" : "2pl",
		"number" : "pl",
		"polypersonal_subject" : null,
		"polypersonal_dobj" : null,
		"polypersonal_iobj" : null,
		"conjugated_form" : "გიცხოვრიათ",
		"normalized_form" : "გიცხოვრიათ",
		"morphemes" : "[\"გი\", \"ცხოვრ\", \"იათ\"]",
		"ipa" : null,
		"audio_url" : null,
		"notes" : null,
		"created_at" : "2025-08-29T14:39:09.000Z"
	},
	{
		"id" : 54,
		"verb_id" : 1,
		"tense" : "perfect",
		"mood" : "indicative",
		"aspect" : null,
		"voice" : null,
		"person" : "3pl",
		"number" : "pl",
		"polypersonal_subject" : null,
		"polypersonal_dobj" : null,
		"polypersonal_iobj" : null,
		"conjugated_form" : "უცხოვრიათ",
		"normalized_form" : "უცხოვრიათ",
		"morphemes" : "[\"უ\", \"ცხოვრ\", \"იათ\"]",
		"ipa" : null,
		"audio_url" : null,
		"notes" : null,
		"created_at" : "2025-08-29T14:39:09.000Z"
	},
	{
		"id" : 55,
		"verb_id" : 1,
		"tense" : "pluperfect",
		"mood" : "indicative",
		"aspect" : null,
		"voice" : null,
		"person" : "1sg",
		"number" : "sg",
		"polypersonal_subject" : null,
		"polypersonal_dobj" : null,
		"polypersonal_iobj" : null,
		"conjugated_form" : "მეცხოვრა",
		"normalized_form" : "მეცხოვრა",
		"morphemes" : "[\"მე\", \"ცხოვრ\", \"ა\"]",
		"ipa" : null,
		"audio_url" : null,
		"notes" : null,
		"created_at" : "2025-08-29T14:39:09.000Z"
	},
	{
		"id" : 56,
		"verb_id" : 1,
		"tense" : "pluperfect",
		"mood" : "indicative",
		"aspect" : null,
		"voice" : null,
		"person" : "2sg",
		"number" : "sg",
		"polypersonal_subject" : null,
		"polypersonal_dobj" : null,
		"polypersonal_iobj" : null,
		"conjugated_form" : "გეცხოვრა",
		"normalized_form" : "გეცხოვრა",
		"morphemes" : "[\"გე\", \"ცხოვრ\", \"ა\"]",
		"ipa" : null,
		"audio_url" : null,
		"notes" : null,
		"created_at" : "2025-08-29T14:39:09.000Z"
	},
	{
		"id" : 57,
		"verb_id" : 1,
		"tense" : "pluperfect",
		"mood" : "indicative",
		"aspect" : null,
		"voice" : null,
		"person" : "3sg",
		"number" : "sg",
		"polypersonal_subject" : null,
		"polypersonal_dobj" : null,
		"polypersonal_iobj" : null,
		"conjugated_form" : "ეცხოვრა",
		"normalized_form" : "ეცხოვრა",
		"morphemes" : "[\"ე\", \"ცხოვრ\", \"ა\"]",
		"ipa" : null,
		"audio_url" : null,
		"notes" : null,
		"created_at" : "2025-08-29T14:39:09.000Z"
	},
	{
		"id" : 58,
		"verb_id" : 1,
		"tense" : "pluperfect",
		"mood" : "indicative",
		"aspect" : null,
		"voice" : null,
		"person" : "1pl",
		"number" : "pl",
		"polypersonal_subject" : null,
		"polypersonal_dobj" : null,
		"polypersonal_iobj" : null,
		"conjugated_form" : "გვეცხოვრა",
		"normalized_form" : "გვეცხოვრა",
		"morphemes" : "[\"გვე\", \"ცხოვრ\", \"ა\"]",
		"ipa" : null,
		"audio_url" : null,
		"notes" : null,
		"created_at" : "2025-08-29T14:39:09.000Z"
	},
	{
		"id" : 59,
		"verb_id" : 1,
		"tense" : "pluperfect",
		"mood" : "indicative",
		"aspect" : null,
		"voice" : null,
		"person" : "2pl",
		"number" : "pl",
		"polypersonal_subject" : null,
		"polypersonal_dobj" : null,
		"polypersonal_iobj" : null,
		"conjugated_form" : "გეცხოვრათ",
		"normalized_form" : "გეცხოვრათ",
		"morphemes" : "[\"გე\", \"ცხოვრ\", \"ათ\"]",
		"ipa" : null,
		"audio_url" : null,
		"notes" : null,
		"created_at" : "2025-08-29T14:39:09.000Z"
	},
	{
		"id" : 60,
		"verb_id" : 1,
		"tense" : "pluperfect",
		"mood" : "indicative",
		"aspect" : null,
		"voice" : null,
		"person" : "3pl",
		"number" : "pl",
		"polypersonal_subject" : null,
		"polypersonal_dobj" : null,
		"polypersonal_iobj" : null,
		"conjugated_form" : "ეცხოვრათ",
		"normalized_form" : "ეცხოვრათ",
		"morphemes" : "[\"ე\", \"ცხოვრ\", \"ათ\"]",
		"ipa" : null,
		"audio_url" : null,
		"notes" : null,
		"created_at" : "2025-08-29T14:39:09.000Z"
	},
	{
		"id" : 253,
		"verb_id" : 13,
		"tense" : "presente",
		"mood" : "indicative",
		"aspect" : null,
		"voice" : null,
		"person" : "1sg",
		"number" : "sg",
		"polypersonal_subject" : null,
		"polypersonal_dobj" : null,
		"polypersonal_iobj" : null,
		"conjugated_form" : "ვწერ",
		"normalized_form" : "ვწერ",
		"morphemes" : "[\"ვ\", \"წერ\"]",
		"ipa" : null,
		"audio_url" : null,
		"notes" : null,
		"created_at" : "2025-08-29T14:47:08.000Z"
	},
	{
		"id" : 254,
		"verb_id" : 13,
		"tense" : "presente",
		"mood" : "indicative",
		"aspect" : null,
		"voice" : null,
		"person" : "2sg",
		"number" : "sg",
		"polypersonal_subject" : null,
		"polypersonal_dobj" : null,
		"polypersonal_iobj" : null,
		"conjugated_form" : "წერ",
		"normalized_form" : "წერ",
		"morphemes" : "[\"წერ\"]",
		"ipa" : null,
		"audio_url" : null,
		"notes" : null,
		"created_at" : "2025-08-29T14:47:08.000Z"
	},
	{
		"id" : 255,
		"verb_id" : 13,
		"tense" : "presente",
		"mood" : "indicative",
		"aspect" : null,
		"voice" : null,
		"person" : "3sg",
		"number" : "sg",
		"polypersonal_subject" : null,
		"polypersonal_dobj" : null,
		"polypersonal_iobj" : null,
		"conjugated_form" : "წერს",
		"normalized_form" : "წერს",
		"morphemes" : "[\"წერ\", \"ს\"]",
		"ipa" : null,
		"audio_url" : null,
		"notes" : null,
		"created_at" : "2025-08-29T14:47:08.000Z"
	},
	{
		"id" : 256,
		"verb_id" : 13,
		"tense" : "presente",
		"mood" : "indicative",
		"aspect" : null,
		"voice" : null,
		"person" : "1pl",
		"number" : "pl",
		"polypersonal_subject" : null,
		"polypersonal_dobj" : null,
		"polypersonal_iobj" : null,
		"conjugated_form" : "ვწერთ",
		"normalized_form" : "ვწერთ",
		"morphemes" : "[\"ვ\", \"წერ\", \"თ\"]",
		"ipa" : null,
		"audio_url" : null,
		"notes" : null,
		"created_at" : "2025-08-29T14:47:08.000Z"
	},
	{
		"id" : 257,
		"verb_id" : 13,
		"tense" : "presente",
		"mood" : "indicative",
		"aspect" : null,
		"voice" : null,
		"person" : "2pl",
		"number" : "pl",
		"polypersonal_subject" : null,
		"polypersonal_dobj" : null,
		"polypersonal_iobj" : null,
		"conjugated_form" : "წერთ",
		"normalized_form" : "წერთ",
		"morphemes" : "[\"წერ\", \"თ\"]",
		"ipa" : null,
		"audio_url" : null,
		"notes" : null,
		"created_at" : "2025-08-29T14:47:08.000Z"
	},
	{
		"id" : 258,
		"verb_id" : 13,
		"tense" : "presente",
		"mood" : "indicative",
		"aspect" : null,
		"voice" : null,
		"person" : "3pl",
		"number" : "pl",
		"polypersonal_subject" : null,
		"polypersonal_dobj" : null,
		"polypersonal_iobj" : null,
		"conjugated_form" : "წერენ",
		"normalized_form" : "წერენ",
		"morphemes" : "[\"წერ\", \"ენ\"]",
		"ipa" : null,
		"audio_url" : null,
		"notes" : null,
		"created_at" : "2025-08-29T14:47:08.000Z"
	},
	{
		"id" : 259,
		"verb_id" : 13,
		"tense" : "imperfect",
		"mood" : "indicative",
		"aspect" : null,
		"voice" : null,
		"person" : "1sg",
		"number" : "sg",
		"polypersonal_subject" : null,
		"polypersonal_dobj" : null,
		"polypersonal_iobj" : null,
		"conjugated_form" : "ვწერდი",
		"normalized_form" : "ვწერდი",
		"morphemes" : "[\"ვ\", \"წერ\", \"დ\", \"ი\"]",
		"ipa" : null,
		"audio_url" : null,
		"notes" : null,
		"created_at" : "2025-08-29T14:47:08.000Z"
	},
	{
		"id" : 260,
		"verb_id" : 13,
		"tense" : "imperfect",
		"mood" : "indicative",
		"aspect" : null,
		"voice" : null,
		"person" : "2sg",
		"number" : "sg",
		"polypersonal_subject" : null,
		"polypersonal_dobj" : null,
		"polypersonal_iobj" : null,
		"conjugated_form" : "წერდი",
		"normalized_form" : "წერდი",
		"morphemes" : "[\"წერ\", \"დ\", \"ი\"]",
		"ipa" : null,
		"audio_url" : null,
		"notes" : null,
		"created_at" : "2025-08-29T14:47:08.000Z"
	},
	{
		"id" : 261,
		"verb_id" : 13,
		"tense" : "imperfect",
		"mood" : "indicative",
		"aspect" : null,
		"voice" : null,
		"person" : "3sg",
		"number" : "sg",
		"polypersonal_subject" : null,
		"polypersonal_dobj" : null,
		"polypersonal_iobj" : null,
		"conjugated_form" : "წერდა",
		"normalized_form" : "წერდა",
		"morphemes" : "[\"წერ\", \"დ\", \"ა\"]",
		"ipa" : null,
		"audio_url" : null,
		"notes" : null,
		"created_at" : "2025-08-29T14:47:08.000Z"
	},
	{
		"id" : 262,
		"verb_id" : 13,
		"tense" : "imperfect",
		"mood" : "indicative",
		"aspect" : null,
		"voice" : null,
		"person" : "1pl",
		"number" : "pl",
		"polypersonal_subject" : null,
		"polypersonal_dobj" : null,
		"polypersonal_iobj" : null,
		"conjugated_form" : "ვწერდით",
		"normalized_form" : "ვწერდით",
		"morphemes" : "[\"ვ\", \"წერ\", \"დ\", \"ით\"]",
		"ipa" : null,
		"audio_url" : null,
		"notes" : null,
		"created_at" : "2025-08-29T14:47:08.000Z"
	},
	{
		"id" : 263,
		"verb_id" : 13,
		"tense" : "imperfect",
		"mood" : "indicative",
		"aspect" : null,
		"voice" : null,
		"person" : "2pl",
		"number" : "pl",
		"polypersonal_subject" : null,
		"polypersonal_dobj" : null,
		"polypersonal_iobj" : null,
		"conjugated_form" : "წერდით",
		"normalized_form" : "წერდით",
		"morphemes" : "[\"წერ\", \"დ\", \"ით\"]",
		"ipa" : null,
		"audio_url" : null,
		"notes" : null,
		"created_at" : "2025-08-29T14:47:08.000Z"
	},
	{
		"id" : 264,
		"verb_id" : 13,
		"tense" : "imperfect",
		"mood" : "indicative",
		"aspect" : null,
		"voice" : null,
		"person" : "3pl",
		"number" : "pl",
		"polypersonal_subject" : null,
		"polypersonal_dobj" : null,
		"polypersonal_iobj" : null,
		"conjugated_form" : "წერდნენ",
		"normalized_form" : "წერდნენ",
		"morphemes" : "[\"წერ\", \"დ\", \"ნენ\"]",
		"ipa" : null,
		"audio_url" : null,
		"notes" : null,
		"created_at" : "2025-08-29T14:47:08.000Z"
	},
	{
		"id" : 265,
		"verb_id" : 13,
		"tense" : "present",
		"mood" : "subjunctive",
		"aspect" : null,
		"voice" : null,
		"person" : "1sg",
		"number" : "sg",
		"polypersonal_subject" : null,
		"polypersonal_dobj" : null,
		"polypersonal_iobj" : null,
		"conjugated_form" : "ვწერდე",
		"normalized_form" : "ვწერდე",
		"morphemes" : "[\"ვ\", \"წერ\", \"დ\", \"ე\"]",
		"ipa" : null,
		"audio_url" : null,
		"notes" : null,
		"created_at" : "2025-08-29T14:47:08.000Z"
	},
	{
		"id" : 266,
		"verb_id" : 13,
		"tense" : "present",
		"mood" : "subjunctive",
		"aspect" : null,
		"voice" : null,
		"person" : "2sg",
		"number" : "sg",
		"polypersonal_subject" : null,
		"polypersonal_dobj" : null,
		"polypersonal_iobj" : null,
		"conjugated_form" : "წერდე",
		"normalized_form" : "წერდე",
		"morphemes" : "[\"წერ\", \"დ\", \"ე\"]",
		"ipa" : null,
		"audio_url" : null,
		"notes" : null,
		"created_at" : "2025-08-29T14:47:08.000Z"
	},
	{
		"id" : 267,
		"verb_id" : 13,
		"tense" : "present",
		"mood" : "subjunctive",
		"aspect" : null,
		"voice" : null,
		"person" : "3sg",
		"number" : "sg",
		"polypersonal_subject" : null,
		"polypersonal_dobj" : null,
		"polypersonal_iobj" : null,
		"conjugated_form" : "წერდეს",
		"normalized_form" : "წერდეს",
		"morphemes" : "[\"წერ\", \"დ\", \"ეს\"]",
		"ipa" : null,
		"audio_url" : null,
		"notes" : null,
		"created_at" : "2025-08-29T14:47:08.000Z"
	},
	{
		"id" : 268,
		"verb_id" : 13,
		"tense" : "present",
		"mood" : "subjunctive",
		"aspect" : null,
		"voice" : null,
		"person" : "1pl",
		"number" : "pl",
		"polypersonal_subject" : null,
		"polypersonal_dobj" : null,
		"polypersonal_iobj" : null,
		"conjugated_form" : "ვწერდეთ",
		"normalized_form" : "ვწერდეთ",
		"morphemes" : "[\"ვ\", \"წერ\", \"დ\", \"ეთ\"]",
		"ipa" : null,
		"audio_url" : null,
		"notes" : null,
		"created_at" : "2025-08-29T14:47:08.000Z"
	},
	{
		"id" : 269,
		"verb_id" : 13,
		"tense" : "present",
		"mood" : "subjunctive",
		"aspect" : null,
		"voice" : null,
		"person" : "2pl",
		"number" : "pl",
		"polypersonal_subject" : null,
		"polypersonal_dobj" : null,
		"polypersonal_iobj" : null,
		"conjugated_form" : "წერდეთ",
		"normalized_form" : "წერდეთ",
		"morphemes" : "[\"წერ\", \"დ\", \"ეთ\"]",
		"ipa" : null,
		"audio_url" : null,
		"notes" : null,
		"created_at" : "2025-08-29T14:47:08.000Z"
	},
	{
		"id" : 270,
		"verb_id" : 13,
		"tense" : "present",
		"mood" : "subjunctive",
		"aspect" : null,
		"voice" : null,
		"person" : "3pl",
		"number" : "pl",
		"polypersonal_subject" : null,
		"polypersonal_dobj" : null,
		"polypersonal_iobj" : null,
		"conjugated_form" : "წერდნენ",
		"normalized_form" : "წერდნენ",
		"morphemes" : "[\"წერ\", \"დ\", \"ნენ\"]",
		"ipa" : null,
		"audio_url" : null,
		"notes" : null,
		"created_at" : "2025-08-29T14:47:08.000Z"
	},
	{
		"id" : 271,
		"verb_id" : 13,
		"tense" : "future",
		"mood" : "indicative",
		"aspect" : null,
		"voice" : null,
		"person" : "1sg",
		"number" : "sg",
		"polypersonal_subject" : null,
		"polypersonal_dobj" : null,
		"polypersonal_iobj" : null,
		"conjugated_form" : "დავწერ",
		"normalized_form" : "დავწერ",
		"morphemes" : "[\"და\", \"ვ\", \"წერ\"]",
		"ipa" : null,
		"audio_url" : null,
		"notes" : null,
		"created_at" : "2025-08-29T14:47:08.000Z"
	},
	{
		"id" : 272,
		"verb_id" : 13,
		"tense" : "future",
		"mood" : "indicative",
		"aspect" : null,
		"voice" : null,
		"person" : "2sg",
		"number" : "sg",
		"polypersonal_subject" : null,
		"polypersonal_dobj" : null,
		"polypersonal_iobj" : null,
		"conjugated_form" : "დაწერ",
		"normalized_form" : "დაწერ",
		"morphemes" : "[\"და\", \"წერ\"]",
		"ipa" : null,
		"audio_url" : null,
		"notes" : null,
		"created_at" : "2025-08-29T14:47:08.000Z"
	},
	{
		"id" : 273,
		"verb_id" : 13,
		"tense" : "future",
		"mood" : "indicative",
		"aspect" : null,
		"voice" : null,
		"person" : "3sg",
		"number" : "sg",
		"polypersonal_subject" : null,
		"polypersonal_dobj" : null,
		"polypersonal_iobj" : null,
		"conjugated_form" : "დაწერს",
		"normalized_form" : "დაწერს",
		"morphemes" : "[\"და\", \"წერ\", \"ს\"]",
		"ipa" : null,
		"audio_url" : null,
		"notes" : null,
		"created_at" : "2025-08-29T14:47:08.000Z"
	},
	{
		"id" : 274,
		"verb_id" : 13,
		"tense" : "future",
		"mood" : "indicative",
		"aspect" : null,
		"voice" : null,
		"person" : "1pl",
		"number" : "pl",
		"polypersonal_subject" : null,
		"polypersonal_dobj" : null,
		"polypersonal_iobj" : null,
		"conjugated_form" : "დავწერთ",
		"normalized_form" : "დავწერთ",
		"morphemes" : "[\"და\", \"ვ\", \"წერ\", \"თ\"]",
		"ipa" : null,
		"audio_url" : null,
		"notes" : null,
		"created_at" : "2025-08-29T14:47:08.000Z"
	},
	{
		"id" : 275,
		"verb_id" : 13,
		"tense" : "future",
		"mood" : "indicative",
		"aspect" : null,
		"voice" : null,
		"person" : "2pl",
		"number" : "pl",
		"polypersonal_subject" : null,
		"polypersonal_dobj" : null,
		"polypersonal_iobj" : null,
		"conjugated_form" : "დაწერთ",
		"normalized_form" : "დაწერთ",
		"morphemes" : "[\"და\", \"წერ\", \"თ\"]",
		"ipa" : null,
		"audio_url" : null,
		"notes" : null,
		"created_at" : "2025-08-29T14:47:08.000Z"
	},
	{
		"id" : 276,
		"verb_id" : 13,
		"tense" : "future",
		"mood" : "indicative",
		"aspect" : null,
		"voice" : null,
		"person" : "3pl",
		"number" : "pl",
		"polypersonal_subject" : null,
		"polypersonal_dobj" : null,
		"polypersonal_iobj" : null,
		"conjugated_form" : "დაწერენ",
		"normalized_form" : "დაწერენ",
		"morphemes" : "[\"და\", \"წერ\", \"ენ\"]",
		"ipa" : null,
		"audio_url" : null,
		"notes" : null,
		"created_at" : "2025-08-29T14:47:08.000Z"
	},
	{
		"id" : 277,
		"verb_id" : 13,
		"tense" : "conditional",
		"mood" : "conditional",
		"aspect" : null,
		"voice" : null,
		"person" : "1sg",
		"number" : "sg",
		"polypersonal_subject" : null,
		"polypersonal_dobj" : null,
		"polypersonal_iobj" : null,
		"conjugated_form" : "დავწერდი",
		"normalized_form" : "დავწერდი",
		"morphemes" : "[\"და\", \"ვ\", \"წერ\", \"დ\", \"ი\"]",
		"ipa" : null,
		"audio_url" : null,
		"notes" : null,
		"created_at" : "2025-08-29T14:47:08.000Z"
	},
	{
		"id" : 278,
		"verb_id" : 13,
		"tense" : "conditional",
		"mood" : "conditional",
		"aspect" : null,
		"voice" : null,
		"person" : "2sg",
		"number" : "sg",
		"polypersonal_subject" : null,
		"polypersonal_dobj" : null,
		"polypersonal_iobj" : null,
		"conjugated_form" : "დაწერდი",
		"normalized_form" : "დაწერდი",
		"morphemes" : "[\"და\", \"წერ\", \"დ\", \"ი\"]",
		"ipa" : null,
		"audio_url" : null,
		"notes" : null,
		"created_at" : "2025-08-29T14:47:08.000Z"
	},
	{
		"id" : 279,
		"verb_id" : 13,
		"tense" : "conditional",
		"mood" : "conditional",
		"aspect" : null,
		"voice" : null,
		"person" : "3sg",
		"number" : "sg",
		"polypersonal_subject" : null,
		"polypersonal_dobj" : null,
		"polypersonal_iobj" : null,
		"conjugated_form" : "დაწერდა",
		"normalized_form" : "დაწერდა",
		"morphemes" : "[\"და\", \"წერ\", \"დ\", \"ა\"]",
		"ipa" : null,
		"audio_url" : null,
		"notes" : null,
		"created_at" : "2025-08-29T14:47:08.000Z"
	},
	{
		"id" : 280,
		"verb_id" : 13,
		"tense" : "conditional",
		"mood" : "conditional",
		"aspect" : null,
		"voice" : null,
		"person" : "1pl",
		"number" : "pl",
		"polypersonal_subject" : null,
		"polypersonal_dobj" : null,
		"polypersonal_iobj" : null,
		"conjugated_form" : "დავწერდით",
		"normalized_form" : "დავწერდით",
		"morphemes" : "[\"და\", \"ვ\", \"წერ\", \"დ\", \"ით\"]",
		"ipa" : null,
		"audio_url" : null,
		"notes" : null,
		"created_at" : "2025-08-29T14:47:08.000Z"
	},
	{
		"id" : 281,
		"verb_id" : 13,
		"tense" : "conditional",
		"mood" : "conditional",
		"aspect" : null,
		"voice" : null,
		"person" : "2pl",
		"number" : "pl",
		"polypersonal_subject" : null,
		"polypersonal_dobj" : null,
		"polypersonal_iobj" : null,
		"conjugated_form" : "დაწერდით",
		"normalized_form" : "დაწერდით",
		"morphemes" : "[\"და\", \"წერ\", \"დ\", \"ით\"]",
		"ipa" : null,
		"audio_url" : null,
		"notes" : null,
		"created_at" : "2025-08-29T14:47:08.000Z"
	},
	{
		"id" : 282,
		"verb_id" : 13,
		"tense" : "conditional",
		"mood" : "conditional",
		"aspect" : null,
		"voice" : null,
		"person" : "3pl",
		"number" : "pl",
		"polypersonal_subject" : null,
		"polypersonal_dobj" : null,
		"polypersonal_iobj" : null,
		"conjugated_form" : "დაწერდნენ",
		"normalized_form" : "დაწერდნენ",
		"morphemes" : "[\"და\", \"წერ\", \"დ\", \"ნენ\"]",
		"ipa" : null,
		"audio_url" : null,
		"notes" : null,
		"created_at" : "2025-08-29T14:47:08.000Z"
	},
	{
		"id" : 283,
		"verb_id" : 13,
		"tense" : "future",
		"mood" : "subjunctive",
		"aspect" : null,
		"voice" : null,
		"person" : "1sg",
		"number" : "sg",
		"polypersonal_subject" : null,
		"polypersonal_dobj" : null,
		"polypersonal_iobj" : null,
		"conjugated_form" : "დავწერდე",
		"normalized_form" : "დავწერდე",
		"morphemes" : "[\"და\", \"ვ\", \"წერ\", \"დ\", \"ე\"]",
		"ipa" : null,
		"audio_url" : null,
		"notes" : null,
		"created_at" : "2025-08-29T14:47:08.000Z"
	},
	{
		"id" : 284,
		"verb_id" : 13,
		"tense" : "future",
		"mood" : "subjunctive",
		"aspect" : null,
		"voice" : null,
		"person" : "2sg",
		"number" : "sg",
		"polypersonal_subject" : null,
		"polypersonal_dobj" : null,
		"polypersonal_iobj" : null,
		"conjugated_form" : "დაწერდე",
		"normalized_form" : "დაწერდე",
		"morphemes" : "[\"და\", \"წერ\", \"დ\", \"ე\"]",
		"ipa" : null,
		"audio_url" : null,
		"notes" : null,
		"created_at" : "2025-08-29T14:47:08.000Z"
	},
	{
		"id" : 285,
		"verb_id" : 13,
		"tense" : "future",
		"mood" : "subjunctive",
		"aspect" : null,
		"voice" : null,
		"person" : "3sg",
		"number" : "sg",
		"polypersonal_subject" : null,
		"polypersonal_dobj" : null,
		"polypersonal_iobj" : null,
		"conjugated_form" : "დაწერდეს",
		"normalized_form" : "დაწერდეს",
		"morphemes" : "[\"და\", \"წერ\", \"დ\", \"ეს\"]",
		"ipa" : null,
		"audio_url" : null,
		"notes" : null,
		"created_at" : "2025-08-29T14:47:08.000Z"
	},
	{
		"id" : 286,
		"verb_id" : 13,
		"tense" : "future",
		"mood" : "subjunctive",
		"aspect" : null,
		"voice" : null,
		"person" : "1pl",
		"number" : "pl",
		"polypersonal_subject" : null,
		"polypersonal_dobj" : null,
		"polypersonal_iobj" : null,
		"conjugated_form" : "დავწერდეთ",
		"normalized_form" : "დავწერდეთ",
		"morphemes" : "[\"და\", \"ვ\", \"წერ\", \"დ\", \"ეთ\"]",
		"ipa" : null,
		"audio_url" : null,
		"notes" : null,
		"created_at" : "2025-08-29T14:47:08.000Z"
	},
	{
		"id" : 287,
		"verb_id" : 13,
		"tense" : "future",
		"mood" : "subjunctive",
		"aspect" : null,
		"voice" : null,
		"person" : "2pl",
		"number" : "pl",
		"polypersonal_subject" : null,
		"polypersonal_dobj" : null,
		"polypersonal_iobj" : null,
		"conjugated_form" : "დაწერდეთ",
		"normalized_form" : "დაწერდეთ",
		"morphemes" : "[\"და\", \"წერ\", \"დ\", \"ეთ\"]",
		"ipa" : null,
		"audio_url" : null,
		"notes" : null,
		"created_at" : "2025-08-29T14:47:08.000Z"
	},
	{
		"id" : 288,
		"verb_id" : 13,
		"tense" : "future",
		"mood" : "subjunctive",
		"aspect" : null,
		"voice" : null,
		"person" : "3pl",
		"number" : "pl",
		"polypersonal_subject" : null,
		"polypersonal_dobj" : null,
		"polypersonal_iobj" : null,
		"conjugated_form" : "დაწერდნენ",
		"normalized_form" : "დაწერდნენ",
		"morphemes" : "[\"და\", \"წერ\", \"დ\", \"ნენ\"]",
		"ipa" : null,
		"audio_url" : null,
		"notes" : null,
		"created_at" : "2025-08-29T14:47:08.000Z"
	},
	{
		"id" : 289,
		"verb_id" : 13,
		"tense" : "aorist",
		"mood" : "aorist",
		"aspect" : null,
		"voice" : null,
		"person" : "1sg",
		"number" : "sg",
		"polypersonal_subject" : null,
		"polypersonal_dobj" : null,
		"polypersonal_iobj" : null,
		"conjugated_form" : "დავწერე",
		"normalized_form" : "დავწერე",
		"morphemes" : "[\"და\", \"ვ\", \"წერ\", \"ე\"]",
		"ipa" : null,
		"audio_url" : null,
		"notes" : null,
		"created_at" : "2025-08-29T14:47:08.000Z"
	},
	{
		"id" : 290,
		"verb_id" : 13,
		"tense" : "aorist",
		"mood" : "aorist",
		"aspect" : null,
		"voice" : null,
		"person" : "2sg",
		"number" : "sg",
		"polypersonal_subject" : null,
		"polypersonal_dobj" : null,
		"polypersonal_iobj" : null,
		"conjugated_form" : "დაწერე",
		"normalized_form" : "დაწერე",
		"morphemes" : "[\"და\", \"წერ\", \"ე\"]",
		"ipa" : null,
		"audio_url" : null,
		"notes" : null,
		"created_at" : "2025-08-29T14:47:08.000Z"
	},
	{
		"id" : 291,
		"verb_id" : 13,
		"tense" : "aorist",
		"mood" : "aorist",
		"aspect" : null,
		"voice" : null,
		"person" : "3sg",
		"number" : "sg",
		"polypersonal_subject" : null,
		"polypersonal_dobj" : null,
		"polypersonal_iobj" : null,
		"conjugated_form" : "დაწერა",
		"normalized_form" : "დაწერა",
		"morphemes" : "[\"და\", \"წერ\", \"ა\"]",
		"ipa" : null,
		"audio_url" : null,
		"notes" : null,
		"created_at" : "2025-08-29T14:47:08.000Z"
	},
	{
		"id" : 292,
		"verb_id" : 13,
		"tense" : "aorist",
		"mood" : "aorist",
		"aspect" : null,
		"voice" : null,
		"person" : "1pl",
		"number" : "pl",
		"polypersonal_subject" : null,
		"polypersonal_dobj" : null,
		"polypersonal_iobj" : null,
		"conjugated_form" : "დავწერეთ",
		"normalized_form" : "დავწერეთ",
		"morphemes" : "[\"და\", \"ვ\", \"წერ\", \"ეთ\"]",
		"ipa" : null,
		"audio_url" : null,
		"notes" : null,
		"created_at" : "2025-08-29T14:47:08.000Z"
	},
	{
		"id" : 293,
		"verb_id" : 13,
		"tense" : "aorist",
		"mood" : "aorist",
		"aspect" : null,
		"voice" : null,
		"person" : "2pl",
		"number" : "pl",
		"polypersonal_subject" : null,
		"polypersonal_dobj" : null,
		"polypersonal_iobj" : null,
		"conjugated_form" : "დაწერეთ",
		"normalized_form" : "დაწერეთ",
		"morphemes" : "[\"და\", \"წერ\", \"ეთ\"]",
		"ipa" : null,
		"audio_url" : null,
		"notes" : null,
		"created_at" : "2025-08-29T14:47:08.000Z"
	},
	{
		"id" : 294,
		"verb_id" : 13,
		"tense" : "aorist",
		"mood" : "aorist",
		"aspect" : null,
		"voice" : null,
		"person" : "3pl",
		"number" : "pl",
		"polypersonal_subject" : null,
		"polypersonal_dobj" : null,
		"polypersonal_iobj" : null,
		"conjugated_form" : "დაწერეს",
		"normalized_form" : "დაწერეს",
		"morphemes" : "[\"და\", \"წერ\", \"ეს\"]",
		"ipa" : null,
		"audio_url" : null,
		"notes" : null,
		"created_at" : "2025-08-29T14:47:08.000Z"
	},
	{
		"id" : 295,
		"verb_id" : 13,
		"tense" : "optative",
		"mood" : "optative",
		"aspect" : null,
		"voice" : null,
		"person" : "1sg",
		"number" : "sg",
		"polypersonal_subject" : null,
		"polypersonal_dobj" : null,
		"polypersonal_iobj" : null,
		"conjugated_form" : "დავწერო",
		"normalized_form" : "დავწერო",
		"morphemes" : "[\"და\", \"ვ\", \"წერ\", \"ო\"]",
		"ipa" : null,
		"audio_url" : null,
		"notes" : null,
		"created_at" : "2025-08-29T14:47:08.000Z"
	},
	{
		"id" : 296,
		"verb_id" : 13,
		"tense" : "optative",
		"mood" : "optative",
		"aspect" : null,
		"voice" : null,
		"person" : "2sg",
		"number" : "sg",
		"polypersonal_subject" : null,
		"polypersonal_dobj" : null,
		"polypersonal_iobj" : null,
		"conjugated_form" : "დაწერო",
		"normalized_form" : "დაწერო",
		"morphemes" : "[\"და\", \"წერ\", \"ო\"]",
		"ipa" : null,
		"audio_url" : null,
		"notes" : null,
		"created_at" : "2025-08-29T14:47:08.000Z"
	},
	{
		"id" : 297,
		"verb_id" : 13,
		"tense" : "optative",
		"mood" : "optative",
		"aspect" : null,
		"voice" : null,
		"person" : "3sg",
		"number" : "sg",
		"polypersonal_subject" : null,
		"polypersonal_dobj" : null,
		"polypersonal_iobj" : null,
		"conjugated_form" : "დაწეროს",
		"normalized_form" : "დაწეროს",
		"morphemes" : "[\"და\", \"წერ\", \"ოს\"]",
		"ipa" : null,
		"audio_url" : null,
		"notes" : null,
		"created_at" : "2025-08-29T14:47:08.000Z"
	},
	{
		"id" : 298,
		"verb_id" : 13,
		"tense" : "optative",
		"mood" : "optative",
		"aspect" : null,
		"voice" : null,
		"person" : "1pl",
		"number" : "pl",
		"polypersonal_subject" : null,
		"polypersonal_dobj" : null,
		"polypersonal_iobj" : null,
		"conjugated_form" : "დავწეროთ",
		"normalized_form" : "დავწეროთ",
		"morphemes" : "[\"და\", \"ვ\", \"წერ\", \"ოთ\"]",
		"ipa" : null,
		"audio_url" : null,
		"notes" : null,
		"created_at" : "2025-08-29T14:47:08.000Z"
	},
	{
		"id" : 299,
		"verb_id" : 13,
		"tense" : "optative",
		"mood" : "optative",
		"aspect" : null,
		"voice" : null,
		"person" : "2pl",
		"number" : "pl",
		"polypersonal_subject" : null,
		"polypersonal_dobj" : null,
		"polypersonal_iobj" : null,
		"conjugated_form" : "დაწეროთ",
		"normalized_form" : "დაწეროთ",
		"morphemes" : "[\"და\", \"წერ\", \"ოთ\"]",
		"ipa" : null,
		"audio_url" : null,
		"notes" : null,
		"created_at" : "2025-08-29T14:47:08.000Z"
	},
	{
		"id" : 300,
		"verb_id" : 13,
		"tense" : "optative",
		"mood" : "optative",
		"aspect" : null,
		"voice" : null,
		"person" : "3pl",
		"number" : "pl",
		"polypersonal_subject" : null,
		"polypersonal_dobj" : null,
		"polypersonal_iobj" : null,
		"conjugated_form" : "დაწერონ",
		"normalized_form" : "დაწერონ",
		"morphemes" : "[\"და\", \"წერ\", \"ონ\"]",
		"ipa" : null,
		"audio_url" : null,
		"notes" : null,
		"created_at" : "2025-08-29T14:47:08.000Z"
	},
	{
		"id" : 301,
		"verb_id" : 13,
		"tense" : "perfect",
		"mood" : "indicative",
		"aspect" : null,
		"voice" : null,
		"person" : "1sg",
		"number" : "sg",
		"polypersonal_subject" : null,
		"polypersonal_dobj" : null,
		"polypersonal_iobj" : null,
		"conjugated_form" : "დამიწერია",
		"normalized_form" : "დამიწერია",
		"morphemes" : "[\"და\", \"მი\", \"წერ\", \"ია\"]",
		"ipa" : null,
		"audio_url" : null,
		"notes" : null,
		"created_at" : "2025-08-29T14:47:08.000Z"
	},
	{
		"id" : 302,
		"verb_id" : 13,
		"tense" : "perfect",
		"mood" : "indicative",
		"aspect" : null,
		"voice" : null,
		"person" : "2sg",
		"number" : "sg",
		"polypersonal_subject" : null,
		"polypersonal_dobj" : null,
		"polypersonal_iobj" : null,
		"conjugated_form" : "დაგიწერია",
		"normalized_form" : "დაგიწერია",
		"morphemes" : "[\"და\", \"გი\", \"წერ\", \"ია\"]",
		"ipa" : null,
		"audio_url" : null,
		"notes" : null,
		"created_at" : "2025-08-29T14:47:08.000Z"
	},
	{
		"id" : 303,
		"verb_id" : 13,
		"tense" : "perfect",
		"mood" : "indicative",
		"aspect" : null,
		"voice" : null,
		"person" : "3sg",
		"number" : "sg",
		"polypersonal_subject" : null,
		"polypersonal_dobj" : null,
		"polypersonal_iobj" : null,
		"conjugated_form" : "დაუწერია",
		"normalized_form" : "დაუწერია",
		"morphemes" : "[\"და\", \"უ\", \"წერ\", \"ია\"]",
		"ipa" : null,
		"audio_url" : null,
		"notes" : null,
		"created_at" : "2025-08-29T14:47:08.000Z"
	},
	{
		"id" : 304,
		"verb_id" : 13,
		"tense" : "perfect",
		"mood" : "indicative",
		"aspect" : null,
		"voice" : null,
		"person" : "1pl",
		"number" : "pl",
		"polypersonal_subject" : null,
		"polypersonal_dobj" : null,
		"polypersonal_iobj" : null,
		"conjugated_form" : "დაგვიწერია",
		"normalized_form" : "დაგვიწერია",
		"morphemes" : "[\"და\", \"გვი\", \"წერ\", \"ია\"]",
		"ipa" : null,
		"audio_url" : null,
		"notes" : null,
		"created_at" : "2025-08-29T14:47:08.000Z"
	},
	{
		"id" : 305,
		"verb_id" : 13,
		"tense" : "perfect",
		"mood" : "indicative",
		"aspect" : null,
		"voice" : null,
		"person" : "2pl",
		"number" : "pl",
		"polypersonal_subject" : null,
		"polypersonal_dobj" : null,
		"polypersonal_iobj" : null,
		"conjugated_form" : "დაგიწერიათ",
		"normalized_form" : "დაგიწერიათ",
		"morphemes" : "[\"და\", \"გი\", \"წერ\", \"იათ\"]",
		"ipa" : null,
		"audio_url" : null,
		"notes" : null,
		"created_at" : "2025-08-29T14:47:08.000Z"
	},
	{
		"id" : 306,
		"verb_id" : 13,
		"tense" : "perfect",
		"mood" : "indicative",
		"aspect" : null,
		"voice" : null,
		"person" : "3pl",
		"number" : "pl",
		"polypersonal_subject" : null,
		"polypersonal_dobj" : null,
		"polypersonal_iobj" : null,
		"conjugated_form" : "დაუწერიათ",
		"normalized_form" : "დაუწერიათ",
		"morphemes" : "[\"და\", \"უ\", \"წერ\", \"იათ\"]",
		"ipa" : null,
		"audio_url" : null,
		"notes" : null,
		"created_at" : "2025-08-29T14:47:08.000Z"
	},
	{
		"id" : 307,
		"verb_id" : 13,
		"tense" : "pluperfect",
		"mood" : "indicative",
		"aspect" : null,
		"voice" : null,
		"person" : "1sg",
		"number" : "sg",
		"polypersonal_subject" : null,
		"polypersonal_dobj" : null,
		"polypersonal_iobj" : null,
		"conjugated_form" : "დამეწერა",
		"normalized_form" : "დამეწერა",
		"morphemes" : "[\"და\", \"მე\", \"წერ\", \"ა\"]",
		"ipa" : null,
		"audio_url" : null,
		"notes" : null,
		"created_at" : "2025-08-29T14:47:08.000Z"
	},
	{
		"id" : 308,
		"verb_id" : 13,
		"tense" : "pluperfect",
		"mood" : "indicative",
		"aspect" : null,
		"voice" : null,
		"person" : "2sg",
		"number" : "sg",
		"polypersonal_subject" : null,
		"polypersonal_dobj" : null,
		"polypersonal_iobj" : null,
		"conjugated_form" : "დაგეწერა",
		"normalized_form" : "დაგეწერა",
		"morphemes" : "[\"და\", \"გე\", \"წერ\", \"ა\"]",
		"ipa" : null,
		"audio_url" : null,
		"notes" : null,
		"created_at" : "2025-08-29T14:47:08.000Z"
	},
	{
		"id" : 309,
		"verb_id" : 13,
		"tense" : "pluperfect",
		"mood" : "indicative",
		"aspect" : null,
		"voice" : null,
		"person" : "3sg",
		"number" : "sg",
		"polypersonal_subject" : null,
		"polypersonal_dobj" : null,
		"polypersonal_iobj" : null,
		"conjugated_form" : "დაეწერა",
		"normalized_form" : "დაეწერა",
		"morphemes" : "[\"და\", \"ე\", \"წერ\", \"ა\"]",
		"ipa" : null,
		"audio_url" : null,
		"notes" : null,
		"created_at" : "2025-08-29T14:47:08.000Z"
	},
	{
		"id" : 310,
		"verb_id" : 13,
		"tense" : "pluperfect",
		"mood" : "indicative",
		"aspect" : null,
		"voice" : null,
		"person" : "1pl",
		"number" : "pl",
		"polypersonal_subject" : null,
		"polypersonal_dobj" : null,
		"polypersonal_iobj" : null,
		"conjugated_form" : "დაგვეწერა",
		"normalized_form" : "დაგვეწერა",
		"morphemes" : "[\"და\", \"გვე\", \"წერ\", \"ა\"]",
		"ipa" : null,
		"audio_url" : null,
		"notes" : null,
		"created_at" : "2025-08-29T14:47:08.000Z"
	},
	{
		"id" : 311,
		"verb_id" : 13,
		"tense" : "pluperfect",
		"mood" : "indicative",
		"aspect" : null,
		"voice" : null,
		"person" : "2pl",
		"number" : "pl",
		"polypersonal_subject" : null,
		"polypersonal_dobj" : null,
		"polypersonal_iobj" : null,
		"conjugated_form" : "დაგეწერათ",
		"normalized_form" : "დაგეწერათ",
		"morphemes" : "[\"და\", \"გე\", \"წერ\", \"ათ\"]",
		"ipa" : null,
		"audio_url" : null,
		"notes" : null,
		"created_at" : "2025-08-29T14:47:08.000Z"
	},
	{
		"id" : 312,
		"verb_id" : 13,
		"tense" : "pluperfect",
		"mood" : "indicative",
		"aspect" : null,
		"voice" : null,
		"person" : "3pl",
		"number" : "pl",
		"polypersonal_subject" : null,
		"polypersonal_dobj" : null,
		"polypersonal_iobj" : null,
		"conjugated_form" : "დაეწერათ",
		"normalized_form" : "დაეწერათ",
		"morphemes" : "[\"და\", \"ე\", \"წერ\", \"ათ\"]",
		"ipa" : null,
		"audio_url" : null,
		"notes" : null,
		"created_at" : "2025-08-29T14:47:08.000Z"
	},
	{
		"id" : 313,
		"verb_id" : 14,
		"tense" : "presente",
		"mood" : "indicative",
		"aspect" : null,
		"voice" : null,
		"person" : "1sg",
		"number" : "sg",
		"polypersonal_subject" : null,
		"polypersonal_dobj" : null,
		"polypersonal_iobj" : null,
		"conjugated_form" : "ვჭამ",
		"normalized_form" : "ვჭამ",
		"morphemes" : "[\"ვ\", \"ჭამ\"]",
		"ipa" : null,
		"audio_url" : null,
		"notes" : null,
		"created_at" : "2025-08-29T14:49:30.000Z"
	},
	{
		"id" : 314,
		"verb_id" : 14,
		"tense" : "presente",
		"mood" : "indicative",
		"aspect" : null,
		"voice" : null,
		"person" : "2sg",
		"number" : "sg",
		"polypersonal_subject" : null,
		"polypersonal_dobj" : null,
		"polypersonal_iobj" : null,
		"conjugated_form" : "ჭამ",
		"normalized_form" : "ჭამ",
		"morphemes" : "[\"ჭამ\"]",
		"ipa" : null,
		"audio_url" : null,
		"notes" : null,
		"created_at" : "2025-08-29T14:49:30.000Z"
	},
	{
		"id" : 315,
		"verb_id" : 14,
		"tense" : "presente",
		"mood" : "indicative",
		"aspect" : null,
		"voice" : null,
		"person" : "3sg",
		"number" : "sg",
		"polypersonal_subject" : null,
		"polypersonal_dobj" : null,
		"polypersonal_iobj" : null,
		"conjugated_form" : "ჭამს",
		"normalized_form" : "ჭამს",
		"morphemes" : "[\"ჭამ\", \"ს\"]",
		"ipa" : null,
		"audio_url" : null,
		"notes" : null,
		"created_at" : "2025-08-29T14:49:30.000Z"
	},
	{
		"id" : 316,
		"verb_id" : 14,
		"tense" : "presente",
		"mood" : "indicative",
		"aspect" : null,
		"voice" : null,
		"person" : "1pl",
		"number" : "pl",
		"polypersonal_subject" : null,
		"polypersonal_dobj" : null,
		"polypersonal_iobj" : null,
		"conjugated_form" : "ვჭამთ",
		"normalized_form" : "ვჭამთ",
		"morphemes" : "[\"ვ\", \"ჭამ\", \"თ\"]",
		"ipa" : null,
		"audio_url" : null,
		"notes" : null,
		"created_at" : "2025-08-29T14:49:30.000Z"
	},
	{
		"id" : 317,
		"verb_id" : 14,
		"tense" : "presente",
		"mood" : "indicative",
		"aspect" : null,
		"voice" : null,
		"person" : "2pl",
		"number" : "pl",
		"polypersonal_subject" : null,
		"polypersonal_dobj" : null,
		"polypersonal_iobj" : null,
		"conjugated_form" : "ჭამთ",
		"normalized_form" : "ჭამთ",
		"morphemes" : "[\"ჭამ\", \"თ\"]",
		"ipa" : null,
		"audio_url" : null,
		"notes" : null,
		"created_at" : "2025-08-29T14:49:30.000Z"
	},
	{
		"id" : 318,
		"verb_id" : 14,
		"tense" : "presente",
		"mood" : "indicative",
		"aspect" : null,
		"voice" : null,
		"person" : "3pl",
		"number" : "pl",
		"polypersonal_subject" : null,
		"polypersonal_dobj" : null,
		"polypersonal_iobj" : null,
		"conjugated_form" : "ჭამენ",
		"normalized_form" : "ჭამენ",
		"morphemes" : "[\"ჭამ\", \"ენ\"]",
		"ipa" : null,
		"audio_url" : null,
		"notes" : null,
		"created_at" : "2025-08-29T14:49:30.000Z"
	},
	{
		"id" : 319,
		"verb_id" : 14,
		"tense" : "imperfect",
		"mood" : "indicative",
		"aspect" : null,
		"voice" : null,
		"person" : "1sg",
		"number" : "sg",
		"polypersonal_subject" : null,
		"polypersonal_dobj" : null,
		"polypersonal_iobj" : null,
		"conjugated_form" : "ვჭამდი",
		"normalized_form" : "ვჭამდი",
		"morphemes" : "[\"ვ\", \"ჭამ\", \"დ\", \"ი\"]",
		"ipa" : null,
		"audio_url" : null,
		"notes" : null,
		"created_at" : "2025-08-29T14:49:30.000Z"
	},
	{
		"id" : 320,
		"verb_id" : 14,
		"tense" : "imperfect",
		"mood" : "indicative",
		"aspect" : null,
		"voice" : null,
		"person" : "2sg",
		"number" : "sg",
		"polypersonal_subject" : null,
		"polypersonal_dobj" : null,
		"polypersonal_iobj" : null,
		"conjugated_form" : "ჭამდი",
		"normalized_form" : "ჭამდი",
		"morphemes" : "[\"ჭამ\", \"დ\", \"ი\"]",
		"ipa" : null,
		"audio_url" : null,
		"notes" : null,
		"created_at" : "2025-08-29T14:49:30.000Z"
	},
	{
		"id" : 321,
		"verb_id" : 14,
		"tense" : "imperfect",
		"mood" : "indicative",
		"aspect" : null,
		"voice" : null,
		"person" : "3sg",
		"number" : "sg",
		"polypersonal_subject" : null,
		"polypersonal_dobj" : null,
		"polypersonal_iobj" : null,
		"conjugated_form" : "ჭამდა",
		"normalized_form" : "ჭამდა",
		"morphemes" : "[\"ჭამ\", \"დ\", \"ა\"]",
		"ipa" : null,
		"audio_url" : null,
		"notes" : null,
		"created_at" : "2025-08-29T14:49:30.000Z"
	},
	{
		"id" : 322,
		"verb_id" : 14,
		"tense" : "imperfect",
		"mood" : "indicative",
		"aspect" : null,
		"voice" : null,
		"person" : "1pl",
		"number" : "pl",
		"polypersonal_subject" : null,
		"polypersonal_dobj" : null,
		"polypersonal_iobj" : null,
		"conjugated_form" : "ვჭამდით",
		"normalized_form" : "ვჭამდით",
		"morphemes" : "[\"ვ\", \"ჭამ\", \"დ\", \"ით\"]",
		"ipa" : null,
		"audio_url" : null,
		"notes" : null,
		"created_at" : "2025-08-29T14:49:30.000Z"
	},
	{
		"id" : 323,
		"verb_id" : 14,
		"tense" : "imperfect",
		"mood" : "indicative",
		"aspect" : null,
		"voice" : null,
		"person" : "2pl",
		"number" : "pl",
		"polypersonal_subject" : null,
		"polypersonal_dobj" : null,
		"polypersonal_iobj" : null,
		"conjugated_form" : "ჭამდით",
		"normalized_form" : "ჭამდით",
		"morphemes" : "[\"ჭამ\", \"დ\", \"ით\"]",
		"ipa" : null,
		"audio_url" : null,
		"notes" : null,
		"created_at" : "2025-08-29T14:49:30.000Z"
	},
	{
		"id" : 324,
		"verb_id" : 14,
		"tense" : "imperfect",
		"mood" : "indicative",
		"aspect" : null,
		"voice" : null,
		"person" : "3pl",
		"number" : "pl",
		"polypersonal_subject" : null,
		"polypersonal_dobj" : null,
		"polypersonal_iobj" : null,
		"conjugated_form" : "ჭამდნენ",
		"normalized_form" : "ჭამდნენ",
		"morphemes" : "[\"ჭამ\", \"დ\", \"ნენ\"]",
		"ipa" : null,
		"audio_url" : null,
		"notes" : null,
		"created_at" : "2025-08-29T14:49:30.000Z"
	},
	{
		"id" : 325,
		"verb_id" : 14,
		"tense" : "present",
		"mood" : "subjunctive",
		"aspect" : null,
		"voice" : null,
		"person" : "1sg",
		"number" : "sg",
		"polypersonal_subject" : null,
		"polypersonal_dobj" : null,
		"polypersonal_iobj" : null,
		"conjugated_form" : "ვჭამდე",
		"normalized_form" : "ვჭამდე",
		"morphemes" : "[\"ვ\", \"ჭამ\", \"დ\", \"ე\"]",
		"ipa" : null,
		"audio_url" : null,
		"notes" : null,
		"created_at" : "2025-08-29T14:49:30.000Z"
	},
	{
		"id" : 326,
		"verb_id" : 14,
		"tense" : "present",
		"mood" : "subjunctive",
		"aspect" : null,
		"voice" : null,
		"person" : "2sg",
		"number" : "sg",
		"polypersonal_subject" : null,
		"polypersonal_dobj" : null,
		"polypersonal_iobj" : null,
		"conjugated_form" : "ჭამდე",
		"normalized_form" : "ჭამდე",
		"morphemes" : "[\"ჭამ\", \"დ\", \"ე\"]",
		"ipa" : null,
		"audio_url" : null,
		"notes" : null,
		"created_at" : "2025-08-29T14:49:30.000Z"
	},
	{
		"id" : 327,
		"verb_id" : 14,
		"tense" : "present",
		"mood" : "subjunctive",
		"aspect" : null,
		"voice" : null,
		"person" : "3sg",
		"number" : "sg",
		"polypersonal_subject" : null,
		"polypersonal_dobj" : null,
		"polypersonal_iobj" : null,
		"conjugated_form" : "ჭამდეს",
		"normalized_form" : "ჭამდეს",
		"morphemes" : "[\"ჭამ\", \"დ\", \"ეს\"]",
		"ipa" : null,
		"audio_url" : null,
		"notes" : null,
		"created_at" : "2025-08-29T14:49:30.000Z"
	},
	{
		"id" : 328,
		"verb_id" : 14,
		"tense" : "present",
		"mood" : "subjunctive",
		"aspect" : null,
		"voice" : null,
		"person" : "1pl",
		"number" : "pl",
		"polypersonal_subject" : null,
		"polypersonal_dobj" : null,
		"polypersonal_iobj" : null,
		"conjugated_form" : "ვჭამდეთ",
		"normalized_form" : "ვჭამდეთ",
		"morphemes" : "[\"ვ\", \"ჭამ\", \"დ\", \"ეთ\"]",
		"ipa" : null,
		"audio_url" : null,
		"notes" : null,
		"created_at" : "2025-08-29T14:49:30.000Z"
	},
	{
		"id" : 329,
		"verb_id" : 14,
		"tense" : "present",
		"mood" : "subjunctive",
		"aspect" : null,
		"voice" : null,
		"person" : "2pl",
		"number" : "pl",
		"polypersonal_subject" : null,
		"polypersonal_dobj" : null,
		"polypersonal_iobj" : null,
		"conjugated_form" : "ჭამდეთ",
		"normalized_form" : "ჭამდეთ",
		"morphemes" : "[\"ჭამ\", \"დ\", \"ეთ\"]",
		"ipa" : null,
		"audio_url" : null,
		"notes" : null,
		"created_at" : "2025-08-29T14:49:30.000Z"
	},
	{
		"id" : 330,
		"verb_id" : 14,
		"tense" : "present",
		"mood" : "subjunctive",
		"aspect" : null,
		"voice" : null,
		"person" : "3pl",
		"number" : "pl",
		"polypersonal_subject" : null,
		"polypersonal_dobj" : null,
		"polypersonal_iobj" : null,
		"conjugated_form" : "ჭამდნენ",
		"normalized_form" : "ჭამდნენ",
		"morphemes" : "[\"ჭამ\", \"დ\", \"ნენ\"]",
		"ipa" : null,
		"audio_url" : null,
		"notes" : null,
		"created_at" : "2025-08-29T14:49:30.000Z"
	},
	{
		"id" : 331,
		"verb_id" : 14,
		"tense" : "future",
		"mood" : "indicative",
		"aspect" : null,
		"voice" : null,
		"person" : "1sg",
		"number" : "sg",
		"polypersonal_subject" : null,
		"polypersonal_dobj" : null,
		"polypersonal_iobj" : null,
		"conjugated_form" : "შევჭამ",
		"normalized_form" : "შევჭამ",
		"morphemes" : "[\"შე\", \"ვ\", \"ჭამ\"]",
		"ipa" : null,
		"audio_url" : null,
		"notes" : null,
		"created_at" : "2025-08-29T14:49:30.000Z"
	},
	{
		"id" : 332,
		"verb_id" : 14,
		"tense" : "future",
		"mood" : "indicative",
		"aspect" : null,
		"voice" : null,
		"person" : "2sg",
		"number" : "sg",
		"polypersonal_subject" : null,
		"polypersonal_dobj" : null,
		"polypersonal_iobj" : null,
		"conjugated_form" : "შეჭამ",
		"normalized_form" : "შეჭამ",
		"morphemes" : "[\"შე\", \"ჭამ\"]",
		"ipa" : null,
		"audio_url" : null,
		"notes" : null,
		"created_at" : "2025-08-29T14:49:30.000Z"
	},
	{
		"id" : 333,
		"verb_id" : 14,
		"tense" : "future",
		"mood" : "indicative",
		"aspect" : null,
		"voice" : null,
		"person" : "3sg",
		"number" : "sg",
		"polypersonal_subject" : null,
		"polypersonal_dobj" : null,
		"polypersonal_iobj" : null,
		"conjugated_form" : "შეჭამს",
		"normalized_form" : "შეჭამს",
		"morphemes" : "[\"შე\", \"ჭამ\", \"ს\"]",
		"ipa" : null,
		"audio_url" : null,
		"notes" : null,
		"created_at" : "2025-08-29T14:49:30.000Z"
	},
	{
		"id" : 334,
		"verb_id" : 14,
		"tense" : "future",
		"mood" : "indicative",
		"aspect" : null,
		"voice" : null,
		"person" : "1pl",
		"number" : "pl",
		"polypersonal_subject" : null,
		"polypersonal_dobj" : null,
		"polypersonal_iobj" : null,
		"conjugated_form" : "შევჭამთ",
		"normalized_form" : "შევჭამთ",
		"morphemes" : "[\"შე\", \"ვ\", \"ჭამ\", \"თ\"]",
		"ipa" : null,
		"audio_url" : null,
		"notes" : null,
		"created_at" : "2025-08-29T14:49:30.000Z"
	},
	{
		"id" : 335,
		"verb_id" : 14,
		"tense" : "future",
		"mood" : "indicative",
		"aspect" : null,
		"voice" : null,
		"person" : "2pl",
		"number" : "pl",
		"polypersonal_subject" : null,
		"polypersonal_dobj" : null,
		"polypersonal_iobj" : null,
		"conjugated_form" : "შეჭამთ",
		"normalized_form" : "შეჭამთ",
		"morphemes" : "[\"შე\", \"ჭამ\", \"თ\"]",
		"ipa" : null,
		"audio_url" : null,
		"notes" : null,
		"created_at" : "2025-08-29T14:49:30.000Z"
	},
	{
		"id" : 336,
		"verb_id" : 14,
		"tense" : "future",
		"mood" : "indicative",
		"aspect" : null,
		"voice" : null,
		"person" : "3pl",
		"number" : "pl",
		"polypersonal_subject" : null,
		"polypersonal_dobj" : null,
		"polypersonal_iobj" : null,
		"conjugated_form" : "შეჭამენ",
		"normalized_form" : "შეჭამენ",
		"morphemes" : "[\"შე\", \"ჭამ\", \"ენ\"]",
		"ipa" : null,
		"audio_url" : null,
		"notes" : null,
		"created_at" : "2025-08-29T14:49:30.000Z"
	},
	{
		"id" : 337,
		"verb_id" : 14,
		"tense" : "conditional",
		"mood" : "conditional",
		"aspect" : null,
		"voice" : null,
		"person" : "1sg",
		"number" : "sg",
		"polypersonal_subject" : null,
		"polypersonal_dobj" : null,
		"polypersonal_iobj" : null,
		"conjugated_form" : "შევჭამდი",
		"normalized_form" : "შევჭამდი",
		"morphemes" : "[\"შე\", \"ვ\", \"ჭამ\", \"დ\", \"ი\"]",
		"ipa" : null,
		"audio_url" : null,
		"notes" : null,
		"created_at" : "2025-08-29T14:49:30.000Z"
	},
	{
		"id" : 338,
		"verb_id" : 14,
		"tense" : "conditional",
		"mood" : "conditional",
		"aspect" : null,
		"voice" : null,
		"person" : "2sg",
		"number" : "sg",
		"polypersonal_subject" : null,
		"polypersonal_dobj" : null,
		"polypersonal_iobj" : null,
		"conjugated_form" : "შეჭამდი",
		"normalized_form" : "შეჭამდი",
		"morphemes" : "[\"შე\", \"ჭამ\", \"დ\", \"ი\"]",
		"ipa" : null,
		"audio_url" : null,
		"notes" : null,
		"created_at" : "2025-08-29T14:49:30.000Z"
	},
	{
		"id" : 339,
		"verb_id" : 14,
		"tense" : "conditional",
		"mood" : "conditional",
		"aspect" : null,
		"voice" : null,
		"person" : "3sg",
		"number" : "sg",
		"polypersonal_subject" : null,
		"polypersonal_dobj" : null,
		"polypersonal_iobj" : null,
		"conjugated_form" : "შეჭამდა",
		"normalized_form" : "შეჭამდა",
		"morphemes" : "[\"შე\", \"ჭამ\", \"დ\", \"ა\"]",
		"ipa" : null,
		"audio_url" : null,
		"notes" : null,
		"created_at" : "2025-08-29T14:49:30.000Z"
	},
	{
		"id" : 340,
		"verb_id" : 14,
		"tense" : "conditional",
		"mood" : "conditional",
		"aspect" : null,
		"voice" : null,
		"person" : "1pl",
		"number" : "pl",
		"polypersonal_subject" : null,
		"polypersonal_dobj" : null,
		"polypersonal_iobj" : null,
		"conjugated_form" : "შევჭამდით",
		"normalized_form" : "შევჭამდით",
		"morphemes" : "[\"შე\", \"ვ\", \"ჭამ\", \"დ\", \"ით\"]",
		"ipa" : null,
		"audio_url" : null,
		"notes" : null,
		"created_at" : "2025-08-29T14:49:30.000Z"
	},
	{
		"id" : 341,
		"verb_id" : 14,
		"tense" : "conditional",
		"mood" : "conditional",
		"aspect" : null,
		"voice" : null,
		"person" : "2pl",
		"number" : "pl",
		"polypersonal_subject" : null,
		"polypersonal_dobj" : null,
		"polypersonal_iobj" : null,
		"conjugated_form" : "შეჭამდით",
		"normalized_form" : "შეჭამდით",
		"morphemes" : "[\"შე\", \"ჭამ\", \"დ\", \"ით\"]",
		"ipa" : null,
		"audio_url" : null,
		"notes" : null,
		"created_at" : "2025-08-29T14:49:30.000Z"
	},
	{
		"id" : 342,
		"verb_id" : 14,
		"tense" : "conditional",
		"mood" : "conditional",
		"aspect" : null,
		"voice" : null,
		"person" : "3pl",
		"number" : "pl",
		"polypersonal_subject" : null,
		"polypersonal_dobj" : null,
		"polypersonal_iobj" : null,
		"conjugated_form" : "შეჭამდნენ",
		"normalized_form" : "შეჭამდნენ",
		"morphemes" : "[\"შე\", \"ჭამ\", \"დ\", \"ნენ\"]",
		"ipa" : null,
		"audio_url" : null,
		"notes" : null,
		"created_at" : "2025-08-29T14:49:30.000Z"
	},
	{
		"id" : 343,
		"verb_id" : 14,
		"tense" : "future",
		"mood" : "subjunctive",
		"aspect" : null,
		"voice" : null,
		"person" : "1sg",
		"number" : "sg",
		"polypersonal_subject" : null,
		"polypersonal_dobj" : null,
		"polypersonal_iobj" : null,
		"conjugated_form" : "შევჭამდე",
		"normalized_form" : "შევჭამდე",
		"morphemes" : "[\"შე\", \"ვ\", \"ჭამ\", \"დ\", \"ე\"]",
		"ipa" : null,
		"audio_url" : null,
		"notes" : null,
		"created_at" : "2025-08-29T14:49:30.000Z"
	},
	{
		"id" : 344,
		"verb_id" : 14,
		"tense" : "future",
		"mood" : "subjunctive",
		"aspect" : null,
		"voice" : null,
		"person" : "2sg",
		"number" : "sg",
		"polypersonal_subject" : null,
		"polypersonal_dobj" : null,
		"polypersonal_iobj" : null,
		"conjugated_form" : "შეჭამდე",
		"normalized_form" : "შეჭამდე",
		"morphemes" : "[\"შე\", \"ჭამ\", \"დ\", \"ე\"]",
		"ipa" : null,
		"audio_url" : null,
		"notes" : null,
		"created_at" : "2025-08-29T14:49:30.000Z"
	},
	{
		"id" : 345,
		"verb_id" : 14,
		"tense" : "future",
		"mood" : "subjunctive",
		"aspect" : null,
		"voice" : null,
		"person" : "3sg",
		"number" : "sg",
		"polypersonal_subject" : null,
		"polypersonal_dobj" : null,
		"polypersonal_iobj" : null,
		"conjugated_form" : "შეჭამდეს",
		"normalized_form" : "შეჭამდეს",
		"morphemes" : "[\"შე\", \"ჭამ\", \"დ\", \"ეს\"]",
		"ipa" : null,
		"audio_url" : null,
		"notes" : null,
		"created_at" : "2025-08-29T14:49:30.000Z"
	},
	{
		"id" : 346,
		"verb_id" : 14,
		"tense" : "future",
		"mood" : "subjunctive",
		"aspect" : null,
		"voice" : null,
		"person" : "1pl",
		"number" : "pl",
		"polypersonal_subject" : null,
		"polypersonal_dobj" : null,
		"polypersonal_iobj" : null,
		"conjugated_form" : "შევჭამდეთ",
		"normalized_form" : "შევჭამდეთ",
		"morphemes" : "[\"შე\", \"ვ\", \"ჭამ\", \"დ\", \"ეთ\"]",
		"ipa" : null,
		"audio_url" : null,
		"notes" : null,
		"created_at" : "2025-08-29T14:49:30.000Z"
	},
	{
		"id" : 347,
		"verb_id" : 14,
		"tense" : "future",
		"mood" : "subjunctive",
		"aspect" : null,
		"voice" : null,
		"person" : "2pl",
		"number" : "pl",
		"polypersonal_subject" : null,
		"polypersonal_dobj" : null,
		"polypersonal_iobj" : null,
		"conjugated_form" : "შეჭამდეთ",
		"normalized_form" : "შეჭამდეთ",
		"morphemes" : "[\"შე\", \"ჭამ\", \"დ\", \"ეთ\"]",
		"ipa" : null,
		"audio_url" : null,
		"notes" : null,
		"created_at" : "2025-08-29T14:49:30.000Z"
	},
	{
		"id" : 348,
		"verb_id" : 14,
		"tense" : "future",
		"mood" : "subjunctive",
		"aspect" : null,
		"voice" : null,
		"person" : "3pl",
		"number" : "pl",
		"polypersonal_subject" : null,
		"polypersonal_dobj" : null,
		"polypersonal_iobj" : null,
		"conjugated_form" : "შეჭამდნენ",
		"normalized_form" : "შეჭამდნენ",
		"morphemes" : "[\"შე\", \"ჭამ\", \"დ\", \"ნენ\"]",
		"ipa" : null,
		"audio_url" : null,
		"notes" : null,
		"created_at" : "2025-08-29T14:49:30.000Z"
	},
	{
		"id" : 349,
		"verb_id" : 14,
		"tense" : "aorist",
		"mood" : "aorist",
		"aspect" : null,
		"voice" : null,
		"person" : "1sg",
		"number" : "sg",
		"polypersonal_subject" : null,
		"polypersonal_dobj" : null,
		"polypersonal_iobj" : null,
		"conjugated_form" : "შევჭამე",
		"normalized_form" : "შევჭამე",
		"morphemes" : "[\"შე\", \"ვ\", \"ჭამ\", \"ე\"]",
		"ipa" : null,
		"audio_url" : null,
		"notes" : null,
		"created_at" : "2025-08-29T14:49:30.000Z"
	},
	{
		"id" : 350,
		"verb_id" : 14,
		"tense" : "aorist",
		"mood" : "aorist",
		"aspect" : null,
		"voice" : null,
		"person" : "2sg",
		"number" : "sg",
		"polypersonal_subject" : null,
		"polypersonal_dobj" : null,
		"polypersonal_iobj" : null,
		"conjugated_form" : "შეჭამე",
		"normalized_form" : "შეჭამე",
		"morphemes" : "[\"შე\", \"ჭამ\", \"ე\"]",
		"ipa" : null,
		"audio_url" : null,
		"notes" : null,
		"created_at" : "2025-08-29T14:49:30.000Z"
	},
	{
		"id" : 351,
		"verb_id" : 14,
		"tense" : "aorist",
		"mood" : "aorist",
		"aspect" : null,
		"voice" : null,
		"person" : "3sg",
		"number" : "sg",
		"polypersonal_subject" : null,
		"polypersonal_dobj" : null,
		"polypersonal_iobj" : null,
		"conjugated_form" : "შეჭამა",
		"normalized_form" : "შეჭამა",
		"morphemes" : "[\"შე\", \"ჭამ\", \"ა\"]",
		"ipa" : null,
		"audio_url" : null,
		"notes" : null,
		"created_at" : "2025-08-29T14:49:30.000Z"
	},
	{
		"id" : 352,
		"verb_id" : 14,
		"tense" : "aorist",
		"mood" : "aorist",
		"aspect" : null,
		"voice" : null,
		"person" : "1pl",
		"number" : "pl",
		"polypersonal_subject" : null,
		"polypersonal_dobj" : null,
		"polypersonal_iobj" : null,
		"conjugated_form" : "შევჭამეთ",
		"normalized_form" : "შევჭამეთ",
		"morphemes" : "[\"შე\", \"ვ\", \"ჭამ\", \"ეთ\"]",
		"ipa" : null,
		"audio_url" : null,
		"notes" : null,
		"created_at" : "2025-08-29T14:49:30.000Z"
	},
	{
		"id" : 353,
		"verb_id" : 14,
		"tense" : "aorist",
		"mood" : "aorist",
		"aspect" : null,
		"voice" : null,
		"person" : "2pl",
		"number" : "pl",
		"polypersonal_subject" : null,
		"polypersonal_dobj" : null,
		"polypersonal_iobj" : null,
		"conjugated_form" : "შეჭამეთ",
		"normalized_form" : "შეჭამეთ",
		"morphemes" : "[\"შე\", \"ჭამ\", \"ეთ\"]",
		"ipa" : null,
		"audio_url" : null,
		"notes" : null,
		"created_at" : "2025-08-29T14:49:30.000Z"
	},
	{
		"id" : 354,
		"verb_id" : 14,
		"tense" : "aorist",
		"mood" : "aorist",
		"aspect" : null,
		"voice" : null,
		"person" : "3pl",
		"number" : "pl",
		"polypersonal_subject" : null,
		"polypersonal_dobj" : null,
		"polypersonal_iobj" : null,
		"conjugated_form" : "შეჭამეს",
		"normalized_form" : "შეჭამეს",
		"morphemes" : "[\"შე\", \"ჭამ\", \"ეს\"]",
		"ipa" : null,
		"audio_url" : null,
		"notes" : null,
		"created_at" : "2025-08-29T14:49:30.000Z"
	},
	{
		"id" : 355,
		"verb_id" : 14,
		"tense" : "optative",
		"mood" : "optative",
		"aspect" : null,
		"voice" : null,
		"person" : "1sg",
		"number" : "sg",
		"polypersonal_subject" : null,
		"polypersonal_dobj" : null,
		"polypersonal_iobj" : null,
		"conjugated_form" : "შევჭამო",
		"normalized_form" : "შევჭამო",
		"morphemes" : "[\"შე\", \"ვ\", \"ჭამ\", \"ო\"]",
		"ipa" : null,
		"audio_url" : null,
		"notes" : null,
		"created_at" : "2025-08-29T14:49:30.000Z"
	},
	{
		"id" : 356,
		"verb_id" : 14,
		"tense" : "optative",
		"mood" : "optative",
		"aspect" : null,
		"voice" : null,
		"person" : "2sg",
		"number" : "sg",
		"polypersonal_subject" : null,
		"polypersonal_dobj" : null,
		"polypersonal_iobj" : null,
		"conjugated_form" : "შეჭამო",
		"normalized_form" : "შეჭამო",
		"morphemes" : "[\"შე\", \"ჭამ\", \"ო\"]",
		"ipa" : null,
		"audio_url" : null,
		"notes" : null,
		"created_at" : "2025-08-29T14:49:30.000Z"
	},
	{
		"id" : 357,
		"verb_id" : 14,
		"tense" : "optative",
		"mood" : "optative",
		"aspect" : null,
		"voice" : null,
		"person" : "3sg",
		"number" : "sg",
		"polypersonal_subject" : null,
		"polypersonal_dobj" : null,
		"polypersonal_iobj" : null,
		"conjugated_form" : "შეჭამოს",
		"normalized_form" : "შეჭამოს",
		"morphemes" : "[\"შე\", \"ჭამ\", \"ოს\"]",
		"ipa" : null,
		"audio_url" : null,
		"notes" : null,
		"created_at" : "2025-08-29T14:49:30.000Z"
	},
	{
		"id" : 358,
		"verb_id" : 14,
		"tense" : "optative",
		"mood" : "optative",
		"aspect" : null,
		"voice" : null,
		"person" : "1pl",
		"number" : "pl",
		"polypersonal_subject" : null,
		"polypersonal_dobj" : null,
		"polypersonal_iobj" : null,
		"conjugated_form" : "შევჭამოთ",
		"normalized_form" : "შევჭამოთ",
		"morphemes" : "[\"შე\", \"ვ\", \"ჭამ\", \"ოთ\"]",
		"ipa" : null,
		"audio_url" : null,
		"notes" : null,
		"created_at" : "2025-08-29T14:49:30.000Z"
	},
	{
		"id" : 359,
		"verb_id" : 14,
		"tense" : "optative",
		"mood" : "optative",
		"aspect" : null,
		"voice" : null,
		"person" : "2pl",
		"number" : "pl",
		"polypersonal_subject" : null,
		"polypersonal_dobj" : null,
		"polypersonal_iobj" : null,
		"conjugated_form" : "შეჭამოთ",
		"normalized_form" : "შეჭამოთ",
		"morphemes" : "[\"შე\", \"ჭამ\", \"ოთ\"]",
		"ipa" : null,
		"audio_url" : null,
		"notes" : null,
		"created_at" : "2025-08-29T14:49:30.000Z"
	},
	{
		"id" : 360,
		"verb_id" : 14,
		"tense" : "optative",
		"mood" : "optative",
		"aspect" : null,
		"voice" : null,
		"person" : "3pl",
		"number" : "pl",
		"polypersonal_subject" : null,
		"polypersonal_dobj" : null,
		"polypersonal_iobj" : null,
		"conjugated_form" : "შეჭამონ",
		"normalized_form" : "შეჭამონ",
		"morphemes" : "[\"შე\", \"ჭამ\", \"ონ\"]",
		"ipa" : null,
		"audio_url" : null,
		"notes" : null,
		"created_at" : "2025-08-29T14:49:30.000Z"
	},
	{
		"id" : 361,
		"verb_id" : 14,
		"tense" : "perfect",
		"mood" : "indicative",
		"aspect" : null,
		"voice" : null,
		"person" : "1sg",
		"number" : "sg",
		"polypersonal_subject" : null,
		"polypersonal_dobj" : null,
		"polypersonal_iobj" : null,
		"conjugated_form" : "შემიჭამია",
		"normalized_form" : "შემიჭამია",
		"morphemes" : "[\"შე\", \"მი\", \"ჭამ\", \"ია\"]",
		"ipa" : null,
		"audio_url" : null,
		"notes" : null,
		"created_at" : "2025-08-29T14:49:30.000Z"
	},
	{
		"id" : 362,
		"verb_id" : 14,
		"tense" : "perfect",
		"mood" : "indicative",
		"aspect" : null,
		"voice" : null,
		"person" : "2sg",
		"number" : "sg",
		"polypersonal_subject" : null,
		"polypersonal_dobj" : null,
		"polypersonal_iobj" : null,
		"conjugated_form" : "შეგიჭამია",
		"normalized_form" : "შეგიჭამია",
		"morphemes" : "[\"შე\", \"გი\", \"ჭამ\", \"ია\"]",
		"ipa" : null,
		"audio_url" : null,
		"notes" : null,
		"created_at" : "2025-08-29T14:49:30.000Z"
	},
	{
		"id" : 363,
		"verb_id" : 14,
		"tense" : "perfect",
		"mood" : "indicative",
		"aspect" : null,
		"voice" : null,
		"person" : "3sg",
		"number" : "sg",
		"polypersonal_subject" : null,
		"polypersonal_dobj" : null,
		"polypersonal_iobj" : null,
		"conjugated_form" : "შეუჭამია",
		"normalized_form" : "შეუჭამია",
		"morphemes" : "[\"შე\", \"უ\", \"ჭამ\", \"ია\"]",
		"ipa" : null,
		"audio_url" : null,
		"notes" : null,
		"created_at" : "2025-08-29T14:49:30.000Z"
	},
	{
		"id" : 364,
		"verb_id" : 14,
		"tense" : "perfect",
		"mood" : "indicative",
		"aspect" : null,
		"voice" : null,
		"person" : "1pl",
		"number" : "pl",
		"polypersonal_subject" : null,
		"polypersonal_dobj" : null,
		"polypersonal_iobj" : null,
		"conjugated_form" : "შეგვიჭამია",
		"normalized_form" : "შეგვიჭამია",
		"morphemes" : "[\"შე\", \"გვი\", \"ჭამ\", \"ია\"]",
		"ipa" : null,
		"audio_url" : null,
		"notes" : null,
		"created_at" : "2025-08-29T14:49:30.000Z"
	},
	{
		"id" : 365,
		"verb_id" : 14,
		"tense" : "perfect",
		"mood" : "indicative",
		"aspect" : null,
		"voice" : null,
		"person" : "2pl",
		"number" : "pl",
		"polypersonal_subject" : null,
		"polypersonal_dobj" : null,
		"polypersonal_iobj" : null,
		"conjugated_form" : "შეგიჭამიათ",
		"normalized_form" : "შეგიჭამიათ",
		"morphemes" : "[\"შე\", \"გი\", \"ჭამ\", \"იათ\"]",
		"ipa" : null,
		"audio_url" : null,
		"notes" : null,
		"created_at" : "2025-08-29T14:49:30.000Z"
	},
	{
		"id" : 366,
		"verb_id" : 14,
		"tense" : "perfect",
		"mood" : "indicative",
		"aspect" : null,
		"voice" : null,
		"person" : "3pl",
		"number" : "pl",
		"polypersonal_subject" : null,
		"polypersonal_dobj" : null,
		"polypersonal_iobj" : null,
		"conjugated_form" : "შეუჭამიათ",
		"normalized_form" : "შეუჭამიათ",
		"morphemes" : "[\"შე\", \"უ\", \"ჭამ\", \"იათ\"]",
		"ipa" : null,
		"audio_url" : null,
		"notes" : null,
		"created_at" : "2025-08-29T14:49:30.000Z"
	},
	{
		"id" : 367,
		"verb_id" : 14,
		"tense" : "pluperfect",
		"mood" : "indicative",
		"aspect" : null,
		"voice" : null,
		"person" : "1sg",
		"number" : "sg",
		"polypersonal_subject" : null,
		"polypersonal_dobj" : null,
		"polypersonal_iobj" : null,
		"conjugated_form" : "შემეჭამა",
		"normalized_form" : "შემეჭამა",
		"morphemes" : "[\"შე\", \"მე\", \"ჭამ\", \"ა\"]",
		"ipa" : null,
		"audio_url" : null,
		"notes" : null,
		"created_at" : "2025-08-29T14:49:30.000Z"
	},
	{
		"id" : 368,
		"verb_id" : 14,
		"tense" : "pluperfect",
		"mood" : "indicative",
		"aspect" : null,
		"voice" : null,
		"person" : "2sg",
		"number" : "sg",
		"polypersonal_subject" : null,
		"polypersonal_dobj" : null,
		"polypersonal_iobj" : null,
		"conjugated_form" : "შეგეჭამა",
		"normalized_form" : "შეგეჭამა",
		"morphemes" : "[\"შე\", \"გე\", \"ჭამ\", \"ა\"]",
		"ipa" : null,
		"audio_url" : null,
		"notes" : null,
		"created_at" : "2025-08-29T14:49:30.000Z"
	},
	{
		"id" : 369,
		"verb_id" : 14,
		"tense" : "pluperfect",
		"mood" : "indicative",
		"aspect" : null,
		"voice" : null,
		"person" : "3sg",
		"number" : "sg",
		"polypersonal_subject" : null,
		"polypersonal_dobj" : null,
		"polypersonal_iobj" : null,
		"conjugated_form" : "შეეჭამა",
		"normalized_form" : "შეეჭამა",
		"morphemes" : "[\"შე\", \"ე\", \"ჭამ\", \"ა\"]",
		"ipa" : null,
		"audio_url" : null,
		"notes" : null,
		"created_at" : "2025-08-29T14:49:30.000Z"
	},
	{
		"id" : 370,
		"verb_id" : 14,
		"tense" : "pluperfect",
		"mood" : "indicative",
		"aspect" : null,
		"voice" : null,
		"person" : "1pl",
		"number" : "pl",
		"polypersonal_subject" : null,
		"polypersonal_dobj" : null,
		"polypersonal_iobj" : null,
		"conjugated_form" : "შეგვეჭამა",
		"normalized_form" : "შეგვეჭამა",
		"morphemes" : "[\"შე\", \"გვე\", \"ჭამ\", \"ა\"]",
		"ipa" : null,
		"audio_url" : null,
		"notes" : null,
		"created_at" : "2025-08-29T14:49:30.000Z"
	},
	{
		"id" : 371,
		"verb_id" : 14,
		"tense" : "pluperfect",
		"mood" : "indicative",
		"aspect" : null,
		"voice" : null,
		"person" : "2pl",
		"number" : "pl",
		"polypersonal_subject" : null,
		"polypersonal_dobj" : null,
		"polypersonal_iobj" : null,
		"conjugated_form" : "შეგეჭამათ",
		"normalized_form" : "შეგეჭამათ",
		"morphemes" : "[\"შე\", \"გე\", \"ჭამ\", \"ათ\"]",
		"ipa" : null,
		"audio_url" : null,
		"notes" : null,
		"created_at" : "2025-08-29T14:49:30.000Z"
	},
	{
		"id" : 372,
		"verb_id" : 14,
		"tense" : "pluperfect",
		"mood" : "indicative",
		"aspect" : null,
		"voice" : null,
		"person" : "3pl",
		"number" : "pl",
		"polypersonal_subject" : null,
		"polypersonal_dobj" : null,
		"polypersonal_iobj" : null,
		"conjugated_form" : "შეეჭამათ",
		"normalized_form" : "შეეჭამათ",
		"morphemes" : "[\"შე\", \"ე\", \"ჭამ\", \"ათ\"]",
		"ipa" : null,
		"audio_url" : null,
		"notes" : null,
		"created_at" : "2025-08-29T14:49:30.000Z"
	}
]